[
{
"id":"mk19_bb_gm_s1",
"title":{
"__html":"Biostatistics"
},
"childHlIds":[
"f8f777"
],
"childSections":[
{
"id":"mk19_bb_gm_s1_1",
"title":{
"__html":"Sensitivity, Specificity, Predictive Values, and Likelihood Ratios"
},
"childHlIds":[
"e872e0",
"442b92",
"1c6c02",
"55a665",
"d89e09",
"b4dc41",
"16f091",
"f96e2d",
"b4860d",
"07890d"
]
},
{
"id":"mk19_bb_gm_s1_2",
"title":{
"__html":"Study Designs"
},
"childHlIds":[
"83648e"
]
},
{
"id":"mk19_bb_gm_s1_3",
"title":{
"__html":"Risk Estimates"
},
"childHlIds":[
"039e25",
"72b8c7",
"de9227",
"6d3fbc"
]
},
{
"id":"mk19_bb_gm_s1_4",
"title":{
"__html":"Confidence Interval"
},
"childHlIds":[
"32cf27",
"024ef6",
"6c8a87"
]
},
{
"id":"mk19_bb_gm_s1_5",
"title":{
"__html":"<i>P</i> Values, Type I and Type II Errors in Clinical Research"
},
"childHlIds":[
"4a9ea5",
"8e6fdd",
"f5bb1d",
"0f8fb5"
]
},
{
"id":"mk19_bb_gm_s1_6",
"title":{
"__html":"Test Yourself"
},
"childHlIds":[
"7866cc",
"e64a04",
"14db33",
"39b95b",
"5d5c80"
]
}
],
"number":1
},
{
"id":"mk19_bb_gm_s2",
"title":{
"__html":"Medical Ethics and Professionalism"
},
"childHlIds":[
"316b20"
],
"childSections":[
{
"id":"mk19_bb_gm_s2_1",
"title":{
"__html":"Patient Privacy"
},
"childHlIds":[
"e3bf1b",
"33cfbd"
]
},
{
"id":"mk19_bb_gm_s2_2",
"title":{
"__html":"Test Yourself"
},
"childHlIds":[
"7866cc",
"fc2cfe",
"1f2bb6"
]
},
{
"id":"mk19_bb_gm_s2_3",
"title":{
"__html":"Advance Planning"
},
"childHlIds":[
"fb9ffa",
"290bbf",
"89d7ea",
"410130",
"4543b5",
"f3aced",
"a63506"
]
},
{
"id":"mk19_bb_gm_s2_4",
"title":{
"__html":"Decision-Making Capacity"
},
"childHlIds":[
"93dbea",
"d239a7",
"b1febb",
"047e57",
"5aad8d",
"6e369b",
"0499d1",
"e392f1",
"fea912",
"875911"
]
},
{
"id":"mk19_bb_gm_s2_5",
"title":{
"__html":"Test Yourself"
},
"childHlIds":[
"7866cc",
"d93d97",
"62aecd"
]
},
{
"id":"mk19_bb_gm_s2_6",
"title":{
"__html":"Withholding or Withdrawing Treatment"
},
"childHlIds":[
"44c065",
"1d5ed6",
"3e169c",
"09111f"
]
},
{
"id":"mk19_bb_gm_s2_7",
"title":{
"__html":"Physician-Assisted Death"
},
"childHlIds":[
"3dc09e",
"7886aa"
]
},
{
"id":"mk19_bb_gm_s2_8",
"title":{
"__html":"Disclosing Medical Errors"
},
"childHlIds":[
"571615",
"46543b"
]
},
{
"id":"mk19_bb_gm_s2_9",
"title":{
"__html":"The Impaired Physician"
},
"childHlIds":[
"854ea2",
"9209f5"
]
},
{
"id":"mk19_bb_gm_s2_10",
"title":{
"__html":"Conflict of Interest"
},
"childHlIds":[
"74941b",
"152463"
]
}
],
"number":2
},
{
"id":"mk19_bb_gm_s3",
"title":{
"__html":"Chronic Cough"
},
"childHlIds":[
"0de668"
],
"childSections":[
{
"id":"mk19_bb_gm_s3_1",
"title":{
"__html":"Diagnosis"
},
"childHlIds":[
"523223",
"571e95",
"c76e4b",
"f4b2fd"
]
}
],
"number":3
},
{
"id":"mk19_bb_gm_s4",
"title":{
"__html":"Vertigo"
},
"childHlIds":[
"3ef726"
],
"childSections":[
{
"id":"mk19_bb_gm_s4_1",
"title":{
"__html":"Diagnosis"
},
"childHlIds":[
"523223",
"c5cd0a",
"7a4a8b",
"ec501c",
"94953f",
"983b68",
"8a7d7d",
"7f3f4e",
"bc9deb"
]
},
{
"id":"mk19_bb_gm_s4_2",
"title":{
"__html":"Treatment"
},
"childHlIds":[
"4c4ac0",
"57d385",
"6fa71b",
"befd30",
"3358b7",
"0ef4fe",
"09b4d8"
]
}
],
"number":4
},
{
"id":"mk19_bb_gm_s5",
"title":{
"__html":"Systemic Exertion Intolerance Disease"
},
"childHlIds":[
"353790"
],
"childSections":[
{
"id":"mk19_bb_gm_s5_1",
"title":{
"__html":"Diagnosis"
},
"childHlIds":[
"523223",
"69ca09",
"e30e46"
]
},
{
"id":"mk19_bb_gm_s5_2",
"title":{
"__html":"Treatment"
},
"childHlIds":[
"4c4ac0",
"d424e5",
"b8ba7b"
]
}
],
"number":5
},
{
"id":"mk19_bb_gm_s6",
"title":{
"__html":"Insomnia"
},
"childHlIds":[
"866d81"
],
"childSections":[
{
"id":"mk19_bb_gm_s6_1",
"title":{
"__html":"Diagnosis"
},
"childHlIds":[
"523223",
"4896b5"
]
},
{
"id":"mk19_bb_gm_s6_2",
"title":{
"__html":"Treatment"
},
"childHlIds":[
"4c4ac0",
"dcd965",
"023436",
"aa1678",
"f3b4df",
"0969a0",
"0e5a62",
"a9645a"
]
}
],
"number":6
},
{
"id":"mk19_bb_gm_s7",
"title":{
"__html":"Chronic Venous Insufficiency"
},
"childHlIds":[
"c9f4bd"
],
"childSections":[
{
"id":"mk19_bb_gm_s7_1",
"title":{
"__html":"Diagnosis"
},
"childHlIds":[
"523223",
"72bce3",
"c08b68",
"a302d6",
"eb8f6a",
"de75e0",
"5d24d4",
"c10d6f"
]
},
{
"id":"mk19_bb_gm_s7_2",
"title":{
"__html":"Treatment"
},
"childHlIds":[
"4c4ac0",
"08be40",
"2581d2"
]
}
],
"number":7
},
{
"id":"mk19_bb_gm_s8",
"title":{
"__html":"Syncope"
},
"childHlIds":[
"14359d"
],
"childSections":[
{
"id":"mk19_bb_gm_s8_1",
"title":{
"__html":"Diagnosis"
},
"childHlIds":[
"523223",
"b3d06d",
"22887c",
"8de214",
"68c170",
"b9c9a6",
"90a4cc",
"a1d976"
]
},
{
"id":"mk19_bb_gm_s8_2",
"title":{
"__html":"Testing"
},
"childHlIds":[
"fa6a5a",
"f712a7",
"47dcb5",
"60e2d8",
"fbb284",
"1b610f",
"2c819d",
"b8688c",
"b68c16",
"eff0b9",
"98b044",
"b68934"
]
},
{
"id":"mk19_bb_gm_s8_3",
"title":{
"__html":"Treatment"
},
"childHlIds":[
"4c4ac0",
"5f4d54",
"6adccd"
]
},
{
"id":"mk19_bb_gm_s8_4",
"title":{
"__html":"Test Yourself"
},
"childHlIds":[
"7866cc",
"9a873c",
"6f0895"
]
}
],
"number":8
},
{
"id":"mk19_bb_gm_s9",
"title":{
"__html":"Chronic Noncancer Pain"
},
"childHlIds":[
"5cd042"
],
"childSections":[
{
"id":"mk19_bb_gm_s9_1",
"title":{
"__html":"Diagnosis"
},
"childHlIds":[
"523223",
"a17181"
]
},
{
"id":"mk19_bb_gm_s9_2",
"title":{
"__html":"Treatment"
},
"childHlIds":[
"4c4ac0",
"7392fd",
"97e96b",
"f77dac",
"2c138e",
"9e30b4",
"5f0355",
"3a259c",
"648b30",
"7831d1",
"dcaba7",
"f36a42",
"e6c89a",
"b38edd",
"be0ed8",
"504ebb",
"fcb68e",
"b9f5e4",
"176bbd"
]
}
],
"number":9
},
{
"id":"mk19_bb_gm_s10",
"title":{
"__html":"Palliative Care"
},
"childHlIds":[
"b7230d"
],
"childSections":[
{
"id":"mk19_bb_gm_s10_0",
"title":{
"__html":"Palliative Care"
},
"childHlIds":[
"82d23f"
]
},
{
"id":"mk19_bb_gm_s10_1",
"title":{
"__html":"Acute and Chronic Pain at the End of Life"
},
"childHlIds":[
"089a9c",
"b1bf15",
"9db287",
"1347a8",
"7c4618",
"a42f5c",
"94cc96",
"0bce25",
"43a33f",
"eaed71",
"3c4bc3",
"650199",
"13e76f",
"31ccac",
"bc64aa",
"6f10cd",
"30107f",
"df59a9",
"06abd9",
"012934",
"5bf014"
]
},
{
"id":"mk19_bb_gm_s10_2",
"title":{
"__html":"Dyspnea"
},
"childHlIds":[
"e70b0a",
"4ba2c1",
"86cdf1",
"b1e8fa"
]
},
{
"id":"mk19_bb_gm_s10_3",
"title":{
"__html":"Depression and Anxiety"
},
"childHlIds":[
"e3d63d",
"821f67",
"aaad9e"
]
},
{
"id":"mk19_bb_gm_s10_4",
"title":{
"__html":"Anorexia"
},
"childHlIds":[
"b11759",
"36056d"
]
}
],
"number":10
},
{
"id":"mk19_bb_gm_s11",
"title":{
"__html":"Musculoskeletal Pain"
},
"childHlIds":[
"49e58a"
],
"childSections":[
{
"id":"mk19_bb_gm_s11_1",
"title":{
"__html":"Elbow"
},
"childHlIds":[
"5ea536",
"573f91",
"41dd5c",
"e8cbbe",
"20e949",
"038181"
]
},
{
"id":"mk19_bb_gm_s11_2",
"title":{
"__html":"Back"
},
"childHlIds":[
"0557fa",
"86e19e",
"67e058",
"8cf637",
"aeebc4",
"04065a",
"fa6d36",
"eefb36",
"e4d2a9",
"8ac8dd",
"2fd041",
"3535fa",
"aa37a4",
"57348f",
"4d832a",
"1746fd",
"620fd8",
"e8b3cb",
"fd1b1a",
"4055fb",
"6c3044",
"1b802e",
"a55cdd",
"0ef0da",
"ee6e12",
"a7cb69"
]
},
{
"id":"mk19_bb_gm_s11_3",
"title":{
"__html":"Neck Pain"
},
"childHlIds":[
"d7cc7d",
"5464da",
"506946",
"aa3de0",
"e2254b",
"f49d76",
"833637",
"bd93e8",
"945a1e",
"0211fb",
"2fa91a",
"5f2cc1",
"c5ecf7",
"9e89f4",
"ed0201",
"3427b6",
"849f0f",
"eb75a0"
]
},
{
"id":"mk19_bb_gm_s11_4",
"title":{
"__html":"Knee"
},
"childHlIds":[
"e50c79",
"dd55d6",
"09ef3f",
"cf76f1",
"54d41d",
"da0305",
"666370"
]
},
{
"id":"mk19_bb_gm_s11_5",
"title":{
"__html":"Hip"
},
"childHlIds":[
"afcd5c",
"ccfd60",
"cc22f2",
"4f65d5",
"57578e",
"337f36"
]
},
{
"id":"mk19_bb_gm_s11_6",
"title":{
"__html":"Ankle"
},
"childHlIds":[
"cc8c02",
"e4b114",
"e48138",
"820a56"
]
},
{
"id":"mk19_bb_gm_s11_7",
"title":{
"__html":"Foot"
},
"childHlIds":[
"129e74",
"78d331",
"d7738c",
"99462c"
]
},
{
"id":"mk19_bb_gm_s11_8",
"title":{
"__html":"Hand"
},
"childHlIds":[
"a78b1a",
"a4cd05",
"3ca688"
]
},
{
"id":"mk19_bb_gm_s11_9",
"title":{
"__html":"Shoulder"
},
"childHlIds":[
"83cb4c",
"4dd0c9",
"c84cde",
"fc73a5",
"a995d5",
"92ed7e",
"52d923",
"eff2a0",
"74b6b1",
"d099b9",
"c2b716",
"e2c88f",
"0ba4b3",
"2756ba",
"9bcd98",
"afcd3e",
"82e43b",
"512fb6",
"b0547e",
"b16cb3"
]
}
],
"number":11
},
{
"id":"mk19_bb_gm_s12",
"title":{
"__html":"Dyslipidemia"
},
"childHlIds":[
"5a1567"
],
"childSections":[
{
"id":"mk19_bb_gm_s12_1",
"title":{
"__html":"Diagnosis"
},
"childHlIds":[
"523223",
"f64d83",
"f42699"
]
},
{
"id":"mk19_bb_gm_s12_2",
"title":{
"__html":"Prevention and Treatment"
},
"childHlIds":[
"dfc8fd",
"6d52c5",
"b9fc2f",
"98a4c9",
"2d73e5",
"9409b9",
"bfa058",
"bc39c7",
"f5460e",
"1dc80a",
"af31ee",
"d466a8",
"a2008a",
"17e599",
"d810e6",
"d0db4b",
"f9c22b",
"55c875",
"a12a50",
"57b115",
"b32a94",
"6b7af9",
"81b0c3",
"c7ff88",
"e317c8"
]
}
],
"number":12
},
{
"id":"mk19_bb_gm_s13",
"title":{
"__html":"Depression"
},
"childHlIds":[
"75cde5"
],
"childSections":[
{
"id":"mk19_bb_gm_s13_1",
"title":{
"__html":"Screening"
},
"childHlIds":[
"db7551",
"cd6830",
"2c9a94",
"b95a53",
"c79c98"
]
},
{
"id":"mk19_bb_gm_s13_2",
"title":{
"__html":"Diagnosis"
},
"childHlIds":[
"523223",
"a56591",
"ae17ad",
"25c423",
"7347cb",
"116441",
"96ba12",
"5b792c",
"34563f",
"47fb2e",
"83f2b5",
"d3f400",
"2a1d05",
"119f16",
"dc2fd9",
"b58479",
"60dd49",
"ce6fc0",
"9e1b09",
"1c6cff"
]
},
{
"id":"mk19_bb_gm_s13_3",
"title":{
"__html":"Treatment"
},
"childHlIds":[
"4c4ac0",
"c19aa4",
"a67d0c",
"1f54e6",
"7e3431",
"64796c",
"711a2f",
"e6c332",
"cc1377",
"807f6a",
"082e09"
]
}
],
"number":13
},
{
"id":"mk19_bb_gm_s14",
"title":{
"__html":"Bipolar Disorder"
},
"childHlIds":[
"cd4b33"
],
"childSections":[
{
"id":"mk19_bb_gm_s14_1",
"title":{
"__html":"Diagnosis"
},
"childHlIds":[
"523223",
"02f51d"
]
},
{
"id":"mk19_bb_gm_s14_2",
"title":{
"__html":"Treatment"
},
"childHlIds":[
"4c4ac0",
"084dfb"
]
},
{
"id":"mk19_bb_gm_s14_3",
"title":{
"__html":"Test Yourself"
},
"childHlIds":[
"7866cc",
"6e537b",
"92171c"
]
}
],
"number":14
},
{
"id":"mk19_bb_gm_s15",
"title":{
"__html":"Generalized Anxiety Disorder"
},
"childHlIds":[
"9e8536"
],
"childSections":[
{
"id":"mk19_bb_gm_s15_1",
"title":{
"__html":"Diagnosis"
},
"childHlIds":[
"523223",
"b490ad"
]
},
{
"id":"mk19_bb_gm_s15_2",
"title":{
"__html":"Treatment"
},
"childHlIds":[
"4c4ac0",
"be56f0"
]
}
],
"number":15
},
{
"id":"mk19_bb_gm_s16",
"title":{
"__html":"Social Anxiety Disorder"
},
"childHlIds":[
"e7aa64"
],
"childSections":[
{
"id":"mk19_bb_gm_s16_1",
"title":{
"__html":"Diagnosis"
},
"childHlIds":[
"523223",
"ae0ed1"
]
},
{
"id":"mk19_bb_gm_s16_2",
"title":{
"__html":"Treatment"
},
"childHlIds":[
"4c4ac0",
"b4d2e4"
]
}
],
"number":16
},
{
"id":"mk19_bb_gm_s17",
"title":{
"__html":"Panic Disorder"
},
"childHlIds":[
"3989dc"
],
"childSections":[
{
"id":"mk19_bb_gm_s17_1",
"title":{
"__html":"Diagnosis"
},
"childHlIds":[
"523223",
"9e0b7a",
"1adce3",
"89f9fe",
"2edcc5",
"6e7840",
"7d5feb",
"6a0fed",
"329915"
]
},
{
"id":"mk19_bb_gm_s17_2",
"title":{
"__html":"Treatment"
},
"childHlIds":[
"4c4ac0",
"5efbae",
"3dc4b5"
]
}
],
"number":17
},
{
"id":"mk19_bb_gm_s18",
"title":{
"__html":"Posttraumatic Stress Disorder"
},
"childHlIds":[
"a33967"
],
"childSections":[
{
"id":"mk19_bb_gm_s18_1",
"title":{
"__html":"Diagnosis"
},
"childHlIds":[
"523223",
"a4f8b1",
"6e4e0e",
"af5227",
"767795",
"ad3153",
"a2f2cd"
]
},
{
"id":"mk19_bb_gm_s18_2",
"title":{
"__html":"Treatment"
},
"childHlIds":[
"4c4ac0",
"b00b7c",
"4c333c"
]
}
],
"number":18
},
{
"id":"mk19_bb_gm_s19",
"title":{
"__html":"Obsessive-Compulsive Disorder"
},
"childHlIds":[
"64a2eb"
],
"childSections":[
{
"id":"mk19_bb_gm_s19_1",
"title":{
"__html":"Diagnosis"
},
"childHlIds":[
"523223",
"7c44bc",
"fdcc21"
]
},
{
"id":"mk19_bb_gm_s19_2",
"title":{
"__html":"Treatment"
},
"childHlIds":[
"4c4ac0",
"38a625"
]
}
],
"number":19
},
{
"id":"mk19_bb_gm_s20",
"title":{
"__html":"Smoking Cessation"
},
"childHlIds":[
"226ccb"
],
"childSections":[
{
"id":"mk19_bb_gm_s20_0",
"title":{
"__html":"Smoking Cessation"
},
"childHlIds":[
"35efff"
]
},
{
"id":"mk19_bb_gm_s20_1",
"title":{
"__html":"Treatment"
},
"childHlIds":[
"4c4ac0",
"0c5fbd",
"e7e264",
"ff0750",
"65d124",
"c63c6d",
"a22ed9",
"0beabd",
"3b35d1"
]
}
],
"number":20
},
{
"id":"mk19_bb_gm_s21",
"title":{
"__html":"Alcohol Use Disorder"
},
"childHlIds":[
"363a4f"
],
"childSections":[
{
"id":"mk19_bb_gm_s21_1",
"title":{
"__html":"Screening"
},
"childHlIds":[
"db7551",
"f85384"
]
},
{
"id":"mk19_bb_gm_s21_2",
"title":{
"__html":"Diagnosis"
},
"childHlIds":[
"523223",
"f5dca7",
"2bb049",
"bd1149",
"186a5e",
"ee10a9",
"1f5302",
"740ce2",
"fed602"
]
},
{
"id":"mk19_bb_gm_s21_3",
"title":{
"__html":"Treatment"
},
"childHlIds":[
"4c4ac0",
"d5e7d1",
"bd7149",
"7caf88",
"596831",
"f6258d",
"6b2c66",
"2174dd",
"c4fb87",
"d72eda",
"713552",
"b224fa",
"6269bd",
"bed817",
"76a264"
]
},
{
"id":"mk19_bb_gm_s21_4",
"title":{
"__html":"Test Yourself"
},
"childHlIds":[
"7866cc",
"65c218",
"29e091"
]
}
],
"number":21
},
{
"id":"mk19_bb_gm_s22",
"title":{
"__html":"Opioid Use Disorder"
},
"childHlIds":[
"9b22c9"
],
"childSections":[
{
"id":"mk19_bb_gm_s22_0",
"title":{
"__html":"Opioid Use Disorder"
},
"childHlIds":[
"b527d7"
]
},
{
"id":"mk19_bb_gm_s22_1",
"title":{
"__html":"Treatment"
},
"childHlIds":[
"4c4ac0",
"a028a2"
]
}
],
"number":22
},
{
"id":"mk19_bb_gm_s23",
"title":{
"__html":"Somatic Symptom and Related Disorders"
},
"childHlIds":[
"702a17"
],
"childSections":[
{
"id":"mk19_bb_gm_s23_1",
"title":{
"__html":"Diagnosis"
},
"childHlIds":[
"523223",
"24da1e",
"313308",
"1552dc",
"b3e30f",
"4181c8"
]
},
{
"id":"mk19_bb_gm_s23_2",
"title":{
"__html":"Treatment"
},
"childHlIds":[
"4c4ac0",
"c0c3fd",
"4c7053",
"6a67f5"
]
}
],
"number":23
},
{
"id":"mk19_bb_gm_s24",
"title":{
"__html":"Eating Disorders"
},
"childHlIds":[
"0fbd92"
],
"childSections":[
{
"id":"mk19_bb_gm_s24_1",
"title":{
"__html":"Diagnosis"
},
"childHlIds":[
"523223",
"83944d",
"029e4f",
"7f3d09",
"9279ac",
"10544c",
"a5a6f8",
"0ee201",
"3efd51",
"5c15f4",
"26b0cf"
]
},
{
"id":"mk19_bb_gm_s24_2",
"title":{
"__html":"Treatment"
},
"childHlIds":[
"4c4ac0",
"e91d52",
"38293f",
"6483ca"
]
},
{
"id":"mk19_bb_gm_s24_3",
"title":{
"__html":"Test Yourself"
},
"childHlIds":[
"7866cc",
"be35c6",
"a4075e"
]
}
],
"number":24
},
{
"id":"mk19_bb_gm_s25",
"title":{
"__html":"Schizophrenia"
},
"childHlIds":[
"79ce9b"
],
"childSections":[
{
"id":"mk19_bb_gm_s25_1",
"title":{
"__html":"Diagnosis"
},
"childHlIds":[
"523223",
"0ba38a",
"69d8e7",
"13658f",
"768c90",
"330542",
"e82577",
"90de6e"
]
},
{
"id":"mk19_bb_gm_s25_2",
"title":{
"__html":"Treatment"
},
"childHlIds":[
"4c4ac0",
"ef6fbf"
]
}
],
"number":25
},
{
"id":"mk19_bb_gm_s26",
"title":{
"__html":"Attention-Deficit/Hyperactivity Disorder"
},
"childHlIds":[
"ffdf2b"
],
"childSections":[
{
"id":"mk19_bb_gm_s26_1",
"title":{
"__html":"Diagnosis"
},
"childHlIds":[
"523223",
"bbf432"
]
},
{
"id":"mk19_bb_gm_s26_2",
"title":{
"__html":"Treatment"
},
"childHlIds":[
"4c4ac0",
"4edaa9"
]
}
],
"number":26
},
{
"id":"mk19_bb_gm_s27",
"title":{
"__html":"Falls"
},
"childHlIds":[
"59085d"
],
"childSections":[
{
"id":"mk19_bb_gm_s27_1",
"title":{
"__html":"Diagnosis"
},
"childHlIds":[
"523223",
"a33f63"
]
},
{
"id":"mk19_bb_gm_s27_2",
"title":{
"__html":"Treatment"
},
"childHlIds":[
"4c4ac0",
"b858ed",
"4211ce",
"b83b4d",
"e71061",
"3aecf6",
"946723",
"5215ee"
]
},
{
"id":"mk19_bb_gm_s27_3",
"title":{
"__html":"Test Yourself"
},
"childHlIds":[
"7866cc",
"6d76d5",
"d52dcc"
]
}
],
"number":27
},
{
"id":"mk19_bb_gm_s28",
"title":{
"__html":"Urinary Incontinence"
},
"childHlIds":[
"90daf4"
],
"childSections":[
{
"id":"mk19_bb_gm_s28_0",
"title":{
"__html":"Urinary Incontinence"
},
"childHlIds":[
"ac6740",
"26bab8",
"25ada6"
]
},
{
"id":"mk19_bb_gm_s28_1",
"title":{
"__html":"Test Yourself"
},
"childHlIds":[
"7866cc",
"c813be",
"277bda"
]
}
],
"number":28
},
{
"id":"mk19_bb_gm_s29",
"title":{
"__html":"Pressure Injury"
},
"childHlIds":[
"b00d22"
],
"childSections":[
{
"id":"mk19_bb_gm_s29_1",
"title":{
"__html":"Prevention"
},
"childHlIds":[
"c53b76",
"ed77cb"
]
},
{
"id":"mk19_bb_gm_s29_2",
"title":{
"__html":"Diagnosis"
},
"childHlIds":[
"523223",
"bb17a0"
]
},
{
"id":"mk19_bb_gm_s29_3",
"title":{
"__html":"Treatment"
},
"childHlIds":[
"4c4ac0",
"402f2e",
"afa6da",
"c23044",
"08c2eb",
"c8075f",
"89cf3d",
"5a86a5",
"e62c45",
"402d86",
"789b0e"
]
}
],
"number":29
},
{
"id":"mk19_bb_gm_s30",
"title":{
"__html":"Dermatologic Conditions of Aging"
},
"childHlIds":[
"f46be9"
],
"childSections":[
{
"id":"mk19_bb_gm_s30_0",
"title":{
"__html":"Dermatologic Conditions of Aging"
},
"childHlIds":[
"5df474",
"b47a51",
"37a7ed"
]
}
],
"number":30
},
{
"id":"mk19_bb_gm_s31",
"title":{
"__html":"Screening and Prevention"
},
"childHlIds":[
"fa6ef8"
],
"childSections":[
{
"id":"mk19_bb_gm_s31_0",
"title":{
"__html":"Screening and Prevention"
},
"childHlIds":[
"af4722",
"1cc38d"
]
},
{
"id":"mk19_bb_gm_s31_1",
"title":{
"__html":"Aspirin and Prevention"
},
"childHlIds":[
"ef96af",
"564f50",
"5980d7",
"ecf6b8",
"552ff9",
"b83005",
"fa9a26",
"cce69e"
]
}
],
"number":31
},
{
"id":"mk19_bb_gm_s32",
"title":{
"__html":"Breast Cancer Prevention and Screening"
},
"childHlIds":[
"e9f985"
],
"childSections":[
{
"id":"mk19_bb_gm_s32_1",
"title":{
"__html":"Prevention"
},
"childHlIds":[
"c53b76",
"af0839",
"8e745e",
"65c084",
"b9004d"
]
},
{
"id":"mk19_bb_gm_s32_2",
"title":{
"__html":"Screening"
},
"childHlIds":[
"db7551",
"282091"
]
}
],
"number":32
},
{
"id":"mk19_bb_gm_s33",
"title":{
"__html":"Cervical Cancer Screening"
},
"childHlIds":[
"54105a"
],
"childSections":[
{
"id":"mk19_bb_gm_s33_1",
"title":{
"__html":"Screening"
},
"childHlIds":[
"db7551",
"d94e7a",
"5f2a95",
"87205b",
"d6d8b5",
"2e4810",
"0e4f6b",
"3dbd92",
"e3d764",
"d6b4f4"
]
}
],
"number":33
},
{
"id":"mk19_bb_gm_s34",
"title":{
"__html":"Patient Safety"
},
"childHlIds":[
"7fca8f"
],
"childSections":[
{
"id":"mk19_bb_gm_s34_1",
"title":{
"__html":"Diagnostic Errors"
},
"childHlIds":[
"c6c37b",
"2ee876"
]
},
{
"id":"mk19_bb_gm_s34_2",
"title":{
"__html":"Error Analysis"
},
"childHlIds":[
"7f9ed9",
"890be5"
]
},
{
"id":"mk19_bb_gm_s34_3",
"title":{
"__html":"Quality Improvement"
},
"childHlIds":[
"4878c1",
"82dad2"
]
},
{
"id":"mk19_bb_gm_s34_4",
"title":{
"__html":"Patient Handoffs"
},
"childHlIds":[
"87bd75",
"b1d61a"
]
},
{
"id":"mk19_bb_gm_s34_5",
"title":{
"__html":"Health Information Technology"
},
"childHlIds":[
"1218b5",
"e29e4e"
]
}
],
"number":34
},
{
"id":"mk19_bb_gm_s35",
"title":{
"__html":"Perioperative Medicine"
},
"childHlIds":[
"5e12df"
],
"childSections":[
{
"id":"mk19_bb_gm_s35_1",
"title":{
"__html":"Preoperative Testing"
},
"childHlIds":[
"ca23a4",
"dd743c",
"5ad6c5",
"2dc434"
]
},
{
"id":"mk19_bb_gm_s35_2",
"title":{
"__html":"Cardiovascular Risk Assessment"
},
"childHlIds":[
"f77292",
"2104c0",
"dababe",
"c63790",
"e8afc1",
"5d16f8",
"d960c0",
"d1c016",
"eccb09",
"312134",
"4e4cb5",
"bb4eea",
"77bdff",
"0da424",
"fc9f5d"
]
},
{
"id":"mk19_bb_gm_s35_3",
"title":{
"__html":"Cardiovascular Risk Management"
},
"childHlIds":[
"32efc3",
"579742",
"44fe71",
"18a447",
"7ac194",
"30dc80",
"d7d34e",
"5b0892",
"ae2b5c",
"60197d",
"1a059f"
]
},
{
"id":"mk19_bb_gm_s35_4",
"title":{
"__html":"Pulmonary Perioperative Management"
},
"childHlIds":[
"c69e48",
"2d4dea",
"b95e0a",
"9e70e8",
"eb21a4"
]
},
{
"id":"mk19_bb_gm_s35_5",
"title":{
"__html":"Perioperative Management of Anticoagulant Therapy"
},
"childHlIds":[
"849864",
"71bec9",
"38399e",
"19c0ae",
"c566c3",
"f82f06",
"cfd450",
"da5ef0",
"1d7d49",
"14c1fa",
"f728b5",
"18a1d9",
"2a1889",
"e33703",
"082000",
"66fa1d",
"651e18",
"611499"
]
},
{
"id":"mk19_bb_gm_s35_6",
"title":{
"__html":"Perioperative Management of Antiplatelet Therapy"
},
"childHlIds":[
"b4e124",
"ec2566",
"796e60",
"15e237",
"38dfb1",
"2f8237"
]
}
],
"number":35
},
{
"id":"mk19_bb_gm_s36",
"title":{
"__html":"Obesity"
},
"childHlIds":[
"9f8251"
],
"childSections":[
{
"id":"mk19_bb_gm_s36_1",
"title":{
"__html":"Diagnosis"
},
"childHlIds":[
"523223",
"41a805",
"6e1f73",
"c617c0",
"269938",
"73742f",
"a7f77d"
]
},
{
"id":"mk19_bb_gm_s36_2",
"title":{
"__html":"Treatment"
},
"childHlIds":[
"4c4ac0",
"50a200",
"c8a80e",
"b02501",
"06e975",
"5658f4",
"6c8715",
"b9ecac",
"36046b",
"bbd790",
"4c96fb"
]
},
{
"id":"mk19_bb_gm_s36_3",
"title":{
"__html":"Test Yourself"
},
"childHlIds":[
"7866cc",
"995069",
"00804b"
]
}
],
"number":36
},
{
"id":"mk19_bb_gm_s37",
"title":{
"__html":"Erectile Dysfunction"
},
"childHlIds":[
"ab1668"
],
"childSections":[
{
"id":"mk19_bb_gm_s37_1",
"title":{
"__html":"Diagnosis"
},
"childHlIds":[
"523223",
"a1356e"
]
},
{
"id":"mk19_bb_gm_s37_2",
"title":{
"__html":"Testing"
},
"childHlIds":[
"fa6a5a",
"acb2c0"
]
},
{
"id":"mk19_bb_gm_s37_3",
"title":{
"__html":"Treatment"
},
"childHlIds":[
"4c4ac0",
"1ace91",
"6c705c",
"6e9500"
]
},
{
"id":"mk19_bb_gm_s37_4",
"title":{
"__html":"Test Yourself"
},
"childHlIds":[
"7866cc",
"e6bcf6",
"6f6257"
]
}
],
"number":37
},
{
"id":"mk19_bb_gm_s38",
"title":{
"__html":"Benign Prostatic Hyperplasia"
},
"childHlIds":[
"9e6504"
],
"childSections":[
{
"id":"mk19_bb_gm_s38_1",
"title":{
"__html":"Diagnosis"
},
"childHlIds":[
"523223",
"b12f05"
]
},
{
"id":"mk19_bb_gm_s38_2",
"title":{
"__html":"Treatment"
},
"childHlIds":[
"4c4ac0",
"ac31d1",
"ca8f99",
"7860d6",
"0779c2",
"171699",
"adc2aa",
"5acaeb",
"851fb1"
]
}
],
"number":38
},
{
"id":"mk19_bb_gm_s39",
"title":{
"__html":"Acute Scrotal Pain"
},
"childHlIds":[
"107522"
],
"childSections":[
{
"id":"mk19_bb_gm_s39_1",
"title":{
"__html":"Diagnosis"
},
"childHlIds":[
"523223",
"43f541",
"6ada46",
"c103e6"
]
},
{
"id":"mk19_bb_gm_s39_2",
"title":{
"__html":"Treatment"
},
"childHlIds":[
"4c4ac0",
"d40502",
"2a053d"
]
}
],
"number":39
},
{
"id":"mk19_bb_gm_s40",
"title":{
"__html":"Acute Prostatitis"
},
"childHlIds":[
"15f127"
],
"childSections":[
{
"id":"mk19_bb_gm_s40_1",
"title":{
"__html":"Diagnosis"
},
"childHlIds":[
"523223",
"86cab3"
]
},
{
"id":"mk19_bb_gm_s40_2",
"title":{
"__html":"Treatment"
},
"childHlIds":[
"4c4ac0",
"c2c61f"
]
}
],
"number":40
},
{
"id":"mk19_bb_gm_s41",
"title":{
"__html":"Breast Mass"
},
"childHlIds":[
"dc2a65"
],
"childSections":[
{
"id":"mk19_bb_gm_s41_1",
"title":{
"__html":"Diagnosis"
},
"childHlIds":[
"523223",
"a64fc5",
"f6dda6",
"ed223f",
"d0c177"
]
}
],
"number":41
},
{
"id":"mk19_bb_gm_s42",
"title":{
"__html":"Contraception"
},
"childHlIds":[
"5ed336"
],
"childSections":[
{
"id":"mk19_bb_gm_s42_0",
"title":{
"__html":"Contraception"
},
"childHlIds":[
"4ad97d",
"5199c1",
"bd34da",
"36cd0f",
"aa4273",
"deb303",
"adb52c",
"8ed508",
"1c7019",
"18a9f0",
"166609",
"db9957",
"7e85a4",
"7fd7fc"
]
}
],
"number":42
},
{
"id":"mk19_bb_gm_s43",
"title":{
"__html":"Abnormal Uterine Bleeding"
},
"childHlIds":[
"cff358"
],
"childSections":[
{
"id":"mk19_bb_gm_s43_1",
"title":{
"__html":"Diagnosis"
},
"childHlIds":[
"523223",
"c1dba4",
"eabed7",
"0472d0",
"dd51f3",
"6bc4b8",
"b5b59e",
"36226e",
"d11c1f",
"a6d3b8",
"eff26d",
"c65407"
]
},
{
"id":"mk19_bb_gm_s43_2",
"title":{
"__html":"Treatment"
},
"childHlIds":[
"4c4ac0",
"581241",
"c5da4b",
"5f240b",
"7ce463",
"b78182",
"3bfb33",
"fb8e32",
"97510c",
"352a02",
"3bd83a"
]
}
],
"number":43
},
{
"id":"mk19_bb_gm_s44",
"title":{
"__html":"Dysmenorrhea"
},
"childHlIds":[
"134097"
],
"childSections":[
{
"id":"mk19_bb_gm_s44_1",
"title":{
"__html":"Diagnosis"
},
"childHlIds":[
"523223",
"03d049",
"59296b",
"f91188",
"d09c70",
"d4e6f6"
]
},
{
"id":"mk19_bb_gm_s44_2",
"title":{
"__html":"Treatment"
},
"childHlIds":[
"4c4ac0",
"87d645",
"ba9326"
]
}
],
"number":44
},
{
"id":"mk19_bb_gm_s45",
"title":{
"__html":"Menopause"
},
"childHlIds":[
"caf900"
],
"childSections":[
{
"id":"mk19_bb_gm_s45_1",
"title":{
"__html":"Diagnosis"
},
"childHlIds":[
"523223",
"b11950",
"d07ea6"
]
},
{
"id":"mk19_bb_gm_s45_2",
"title":{
"__html":"Treatment"
},
"childHlIds":[
"4c4ac0",
"0e3be1",
"4547f7",
"314d11",
"1786aa",
"425a3b",
"b76d07",
"78cf1e",
"3b7500",
"d98311",
"0ce1d5",
"99d681"
]
}
],
"number":45
},
{
"id":"mk19_bb_gm_s46",
"title":{
"__html":"Chronic Pelvic Pain"
},
"childHlIds":[
"9d3df4"
],
"childSections":[
{
"id":"mk19_bb_gm_s46_0",
"title":{
"__html":"Chronic Pelvic Pain"
},
"childHlIds":[
"db3550"
]
},
{
"id":"mk19_bb_gm_s46_1",
"title":{
"__html":"Testing"
},
"childHlIds":[
"fa6a5a",
"31d470",
"9b4530"
]
},
{
"id":"mk19_bb_gm_s46_2",
"title":{
"__html":"Endometriosis"
},
"childHlIds":[
"41b2cc",
"0f6d58",
"3e04ea",
"49339c",
"d24107"
]
},
{
"id":"mk19_bb_gm_s46_3",
"title":{
"__html":"Treatment"
},
"childHlIds":[
"4c4ac0",
"aa6025"
]
}
],
"number":46
},
{
"id":"mk19_bb_gm_s47",
"title":{
"__html":"Female Sexual Dysfunction"
},
"childHlIds":[
"f53bdb"
],
"childSections":[
{
"id":"mk19_bb_gm_s47_1",
"title":{
"__html":"Diagnosis and Testing"
},
"childHlIds":[
"d7f1cf",
"0de0ea",
"2a4c2f",
"ea477b",
"fde34e",
"c1bb30",
"59e6ad"
]
},
{
"id":"mk19_bb_gm_s47_2",
"title":{
"__html":"Treatment"
},
"childHlIds":[
"4c4ac0",
"646e46",
"bbbde5",
"55707a",
"e2a986",
"c38290"
]
}
],
"number":47
},
{
"id":"mk19_bb_gm_s48",
"title":{
"__html":"Vaginitis"
},
"childHlIds":[
"cb997f"
],
"childSections":[
{
"id":"mk19_bb_gm_s48_1",
"title":{
"__html":"Diagnosis"
},
"childHlIds":[
"523223",
"d9d021",
"93c53a",
"ec2cf0"
]
},
{
"id":"mk19_bb_gm_s48_2",
"title":{
"__html":"Treatment"
},
"childHlIds":[
"4c4ac0",
"ed7cf1"
]
},
{
"id":"mk19_bb_gm_s48_3",
"title":{
"__html":"Test Yourself"
},
"childHlIds":[
"7866cc",
"9d0683",
"40cd05"
]
}
],
"number":48
},
{
"id":"mk19_bb_gm_s49",
"title":{
"__html":"Intimate Partner Violence"
},
"childHlIds":[
"331a2b"
],
"childSections":[
{
"id":"mk19_bb_gm_s49_1",
"title":{
"__html":"Screening"
},
"childHlIds":[
"db7551",
"bbd05e"
]
},
{
"id":"mk19_bb_gm_s49_2",
"title":{
"__html":"Diagnosis"
},
"childHlIds":[
"523223",
"6161d7",
"2539b5",
"f62898",
"283b16",
"d6cf29",
"0077d2",
"7621df",
"d97433",
"1453f5",
"228a10",
"dc876c",
"3e57c2",
"1e31a3",
"0b54ef",
"af1633",
"05eacb",
"9ecea7"
]
},
{
"id":"mk19_bb_gm_s49_3",
"title":{
"__html":"Treatment"
},
"childHlIds":[
"4c4ac0",
"933a81"
]
}
],
"number":49
},
{
"id":"mk19_bb_gm_s50",
"title":{
"__html":"Eye Disorders"
},
"childHlIds":[
"63bca6"
],
"childSections":[
{
"id":"mk19_bb_gm_s50_1",
"title":{
"__html":"Red Eye"
},
"childHlIds":[
"ba218f",
"326c42",
"37f76b"
]
},
{
"id":"mk19_bb_gm_s50_2",
"title":{
"__html":"Test Yourself"
},
"childHlIds":[
"7866cc",
"d2268d",
"2a5653"
]
},
{
"id":"mk19_bb_gm_s50_3",
"title":{
"__html":"Age-Related Macular Degeneration"
},
"childHlIds":[
"121b4c",
"a7efb2",
"49e657"
]
},
{
"id":"mk19_bb_gm_s50_4",
"title":{
"__html":"Retinal Detachment"
},
"childHlIds":[
"cd29bb",
"b14a5b"
]
},
{
"id":"mk19_bb_gm_s50_5",
"title":{
"__html":"Primary Open-Angle Glaucoma"
},
"childHlIds":[
"b693a6",
"a2a99a"
]
},
{
"id":"mk19_bb_gm_s50_6",
"title":{
"__html":"Cataracts"
},
"childHlIds":[
"6bdaea",
"83f4d2"
]
},
{
"id":"mk19_bb_gm_s50_7",
"title":{
"__html":"Dry Eye"
},
"childHlIds":[
"50de9c",
"8fe5ee"
]
},
{
"id":"mk19_bb_gm_s50_8",
"title":{
"__html":"Corneal Abrasions"
},
"childHlIds":[
"00d08a",
"bfb783"
]
}
],
"number":50
},
{
"id":"mk19_bb_gm_s51",
"title":{
"__html":"Hearing Loss"
},
"childHlIds":[
"a2d834"
],
"childSections":[
{
"id":"mk19_bb_gm_s51_1",
"title":{
"__html":"Diagnosis"
},
"childHlIds":[
"523223",
"992615",
"84ae45"
]
},
{
"id":"mk19_bb_gm_s51_2",
"title":{
"__html":"Testing"
},
"childHlIds":[
"fa6a5a",
"803496"
]
},
{
"id":"mk19_bb_gm_s51_3",
"title":{
"__html":"Treatment"
},
"childHlIds":[
"4c4ac0",
"7d3ca1"
]
},
{
"id":"mk19_bb_gm_s51_4",
"title":{
"__html":"Test Yourself"
},
"childHlIds":[
"7866cc",
"e589f2",
"99daa5"
]
}
],
"number":51
},
{
"id":"mk19_bb_gm_s52",
"title":{
"__html":"Otitis Media"
},
"childHlIds":[
"e82825"
],
"childSections":[
{
"id":"mk19_bb_gm_s52_1",
"title":{
"__html":"Diagnosis"
},
"childHlIds":[
"523223",
"e42e99"
]
},
{
"id":"mk19_bb_gm_s52_2",
"title":{
"__html":"Treatment"
},
"childHlIds":[
"4c4ac0",
"24bc69"
]
}
],
"number":52
},
{
"id":"mk19_bb_gm_s53",
"title":{
"__html":"External Otitis"
},
"childHlIds":[
"882dbf"
],
"childSections":[
{
"id":"mk19_bb_gm_s53_1",
"title":{
"__html":"Diagnosis"
},
"childHlIds":[
"523223",
"7f3808",
"1838e6",
"496492"
]
},
{
"id":"mk19_bb_gm_s53_2",
"title":{
"__html":"Treatment"
},
"childHlIds":[
"4c4ac0",
"bf63b5"
]
},
{
"id":"mk19_bb_gm_s53_3",
"title":{
"__html":"Test Yourself"
},
"childHlIds":[
"7866cc",
"27af7f",
"1015d6"
]
}
],
"number":53
},
{
"id":"mk19_bb_gm_s54",
"title":{
"__html":"Sinusitis"
},
"childHlIds":[
"31e176"
],
"childSections":[
{
"id":"mk19_bb_gm_s54_1",
"title":{
"__html":"Diagnosis"
},
"childHlIds":[
"523223",
"22e48a",
"5510d9",
"1166dd",
"22fcac",
"0347f1"
]
},
{
"id":"mk19_bb_gm_s54_2",
"title":{
"__html":"Testing"
},
"childHlIds":[
"fa6a5a",
"b203a2"
]
},
{
"id":"mk19_bb_gm_s54_3",
"title":{
"__html":"Treatment"
},
"childHlIds":[
"4c4ac0",
"b94146"
]
}
],
"number":54
},
{
"id":"mk19_bb_gm_s55",
"title":{
"__html":"Allergic Rhinitis"
},
"childHlIds":[
"39813c"
],
"childSections":[
{
"id":"mk19_bb_gm_s55_1",
"title":{
"__html":"Diagnosis"
},
"childHlIds":[
"523223",
"b33d67",
"cd5864"
]
},
{
"id":"mk19_bb_gm_s55_2",
"title":{
"__html":"Treatment"
},
"childHlIds":[
"4c4ac0",
"4cf76e",
"74c5b8",
"d5ce7a",
"0fc010",
"381c3e"
]
},
{
"id":"mk19_bb_gm_s55_3",
"title":{
"__html":"Test Yourself"
},
"childHlIds":[
"7866cc",
"1080a4",
"012b4a"
]
}
],
"number":55
},
{
"id":"mk19_bb_gm_s56",
"title":{
"__html":"Epistaxis"
},
"childHlIds":[
"a53257"
],
"childSections":[
{
"id":"mk19_bb_gm_s56_1",
"title":{
"__html":"Diagnosis"
},
"childHlIds":[
"523223",
"526f45"
]
},
{
"id":"mk19_bb_gm_s56_2",
"title":{
"__html":"Treatment"
},
"childHlIds":[
"4c4ac0",
"d943db",
"a0f727"
]
}
],
"number":56
},
{
"id":"mk19_bb_gm_s57",
"title":{
"__html":"Acute Sialadenitis"
},
"childHlIds":[
"b45be7"
],
"childSections":[
{
"id":"mk19_bb_gm_s57_1",
"title":{
"__html":"Diagnosis"
},
"childHlIds":[
"523223",
"74b541"
]
},
{
"id":"mk19_bb_gm_s57_2",
"title":{
"__html":"Treatment"
},
"childHlIds":[
"4c4ac0",
"f56d44"
]
}
],
"number":57
},
{
"id":"mk19_bb_gm_s58",
"title":{
"__html":"Pharyngitis"
},
"childHlIds":[
"b33bb7"
],
"childSections":[
{
"id":"mk19_bb_gm_s58_1",
"title":{
"__html":"Diagnosis"
},
"childHlIds":[
"523223",
"ce46a2",
"eedfcf",
"479a61",
"ba2e76",
"44ecb5",
"9d8c59",
"216ad9",
"6e65f2",
"3a2550"
]
},
{
"id":"mk19_bb_gm_s58_2",
"title":{
"__html":"Treatment"
},
"childHlIds":[
"4c4ac0",
"1814db"
]
}
],
"number":58
},
{
"id":"mk19_bb_gm_s59",
"title":{
"__html":"Oral Infections and Dental Disease"
},
"childHlIds":[
"0764de"
],
"childSections":[
{
"id":"mk19_bb_gm_s59_1",
"title":{
"__html":"Diagnosis"
},
"childHlIds":[
"523223",
"6480ec",
"337e39",
"21723f"
]
},
{
"id":"mk19_bb_gm_s59_2",
"title":{
"__html":"Treatment"
},
"childHlIds":[
"4c4ac0",
"92f4e2",
"8211cd",
"d04833"
]
}
],
"number":59
},
{
"id":"mk19_bb_gm_s60",
"title":{
"__html":"Dermatologic Signs of Systemic Disease"
},
"childHlIds":[
"5cc6d4"
],
"childSections":[
{
"id":"mk19_bb_gm_s60_0",
"title":{
"__html":"Dermatologic Signs of Systemic Disease"
},
"childHlIds":[
"0a2d20"
]
}
],
"number":60
},
{
"id":"mk19_bb_gm_s61",
"title":{
"__html":"Eczemas"
},
"childHlIds":[
"408d7f"
],
"childSections":[
{
"id":"mk19_bb_gm_s61_1",
"title":{
"__html":"Diagnosis"
},
"childHlIds":[
"523223",
"6e0665",
"3a8d7c",
"f4cb63",
"6592e3",
"9fa79a",
"7556a3",
"7b5967",
"80b230",
"35c3cd",
"034ba4",
"f532ba",
"dff8a0",
"24f9d0",
"e2bdf6",
"09d15b",
"70f5ae",
"bfb86f",
"a6b0d4",
"819a7e",
"f6d469",
"f502f1",
"fbae21"
]
},
{
"id":"mk19_bb_gm_s61_2",
"title":{
"__html":"Test Yourself"
},
"childHlIds":[
"7866cc",
"9bf7a3",
"fb8e7d",
"7983e6"
]
},
{
"id":"mk19_bb_gm_s61_3",
"title":{
"__html":"Treatment"
},
"childHlIds":[
"4c4ac0",
"add8e1",
"f5fe92",
"36f7da",
"2b101a",
"4de41a",
"070446",
"437af1",
"2b101a",
"6de6ac",
"d67d36",
"29885a",
"1371ab",
"f10d89",
"250a8b",
"3703bf",
"05312b",
"cfd9d4"
]
},
{
"id":"mk19_bb_gm_s61_4",
"title":{
"__html":"Test Yourself"
},
"childHlIds":[
"7866cc",
"e3e652",
"6ec336"
]
}
],
"number":61
},
{
"id":"mk19_bb_gm_s62",
"title":{
"__html":"Urticaria"
},
"childHlIds":[
"dc0e8a"
],
"childSections":[
{
"id":"mk19_bb_gm_s62_1",
"title":{
"__html":"Diagnosis"
},
"childHlIds":[
"523223",
"1bce52",
"fd66e1",
"a00de7",
"410231",
"c47357",
"1501e8",
"fc6d93"
]
},
{
"id":"mk19_bb_gm_s62_2",
"title":{
"__html":"Treatment"
},
"childHlIds":[
"4c4ac0",
"19eb50",
"ed80f5"
]
},
{
"id":"mk19_bb_gm_s62_3",
"title":{
"__html":"Test Yourself"
},
"childHlIds":[
"7866cc",
"ba39d6",
"062ba8"
]
}
],
"number":62
},
{
"id":"mk19_bb_gm_s63",
"title":{
"__html":"Drug Allergy"
},
"childHlIds":[
"ce2740"
],
"childSections":[
{
"id":"mk19_bb_gm_s63_1",
"title":{
"__html":"Diagnosis"
},
"childHlIds":[
"523223",
"23c812",
"51ea97",
"42173d"
]
},
{
"id":"mk19_bb_gm_s63_2",
"title":{
"__html":"Treatment"
},
"childHlIds":[
"4c4ac0",
"716a65",
"a05e18",
"2f43f8"
]
},
{
"id":"mk19_bb_gm_s63_3",
"title":{
"__html":"Test Yourself"
},
"childHlIds":[
"7866cc",
"1820f4",
"1ee7e5"
]
}
],
"number":63
},
{
"id":"mk19_bb_gm_s64",
"title":{
"__html":"Acneiform Lesions"
},
"childHlIds":[
"41c0da"
],
"childSections":[
{
"id":"mk19_bb_gm_s64_1",
"title":{
"__html":"Diagnosis"
},
"childHlIds":[
"523223",
"40ed22",
"5bf030",
"ce9e44",
"78c700",
"c024c7"
]
},
{
"id":"mk19_bb_gm_s64_2",
"title":{
"__html":"Treatment"
},
"childHlIds":[
"4c4ac0",
"f53a56",
"9661a4",
"545c9c",
"7aeeea"
]
},
{
"id":"mk19_bb_gm_s64_3",
"title":{
"__html":"Test Yourself"
},
"childHlIds":[
"7866cc",
"25941b",
"bfb46d"
]
}
],
"number":64
},
{
"id":"mk19_bb_gm_s65",
"title":{
"__html":"Pemphigus Vulgaris and Pemphigoid"
},
"childHlIds":[
"4444b6"
],
"childSections":[
{
"id":"mk19_bb_gm_s65_1",
"title":{
"__html":"Diagnosis"
},
"childHlIds":[
"523223",
"3824a8",
"e839fc",
"dafec9"
]
},
{
"id":"mk19_bb_gm_s65_2",
"title":{
"__html":"Treatment"
},
"childHlIds":[
"4c4ac0",
"2367e6",
"f06d5c"
]
},
{
"id":"mk19_bb_gm_s65_3",
"title":{
"__html":"Test Yourself"
},
"childHlIds":[
"7866cc",
"baa30a",
"fa591b"
]
}
],
"number":65
},
{
"id":"mk19_bb_gm_s66",
"title":{
"__html":"Dermatophyte and Yeast Infections"
},
"childHlIds":[
"be3064"
],
"childSections":[
{
"id":"mk19_bb_gm_s66_1",
"title":{
"__html":"Diagnosis"
},
"childHlIds":[
"523223",
"2f7714",
"b17b50"
]
},
{
"id":"mk19_bb_gm_s66_2",
"title":{
"__html":"Physical Examination"
},
"childHlIds":[
"94eef1",
"1a612c",
"45fd56",
"aa7725",
"50379a",
"4a5eba",
"53df11",
"06b7b5"
]
},
{
"id":"mk19_bb_gm_s66_3",
"title":{
"__html":"Testing"
},
"childHlIds":[
"fa6a5a",
"4d9f8a",
"0c8ff1",
"f3b72a",
"d40855",
"19e090",
"cd2835"
]
},
{
"id":"mk19_bb_gm_s66_4",
"title":{
"__html":"Treatment"
},
"childHlIds":[
"4c4ac0",
"c7c882",
"22805e",
"c95904",
"b54ed7"
]
},
{
"id":"mk19_bb_gm_s66_5",
"title":{
"__html":"Test Yourself"
},
"childHlIds":[
"7866cc",
"a07d0a",
"36e23c"
]
}
],
"number":66
},
{
"id":"mk19_bb_gm_s67",
"title":{
"__html":"Primary Varicella"
},
"childHlIds":[
"38e4ec"
],
"childSections":[
{
"id":"mk19_bb_gm_s67_1",
"title":{
"__html":"Diagnosis"
},
"childHlIds":[
"523223",
"c029d3"
]
}
],
"number":67
},
{
"id":"mk19_bb_gm_s68",
"title":{
"__html":"Herpes Zoster"
},
"childHlIds":[
"86d959"
],
"childSections":[
{
"id":"mk19_bb_gm_s68_1",
"title":{
"__html":"Prevention"
},
"childHlIds":[
"c53b76",
"ae460f"
]
},
{
"id":"mk19_bb_gm_s68_2",
"title":{
"__html":"Physical Examination"
},
"childHlIds":[
"94eef1",
"a09cba",
"00ffe7",
"8a9cdf",
"5eb716",
"7bff8a"
]
},
{
"id":"mk19_bb_gm_s68_3",
"title":{
"__html":"Testing"
},
"childHlIds":[
"fa6a5a",
"337395"
]
},
{
"id":"mk19_bb_gm_s68_4",
"title":{
"__html":"Treatment"
},
"childHlIds":[
"4c4ac0",
"546a2b",
"c8f7b2",
"9f3a4e",
"c0da2e",
"674405",
"08baf0"
]
},
{
"id":"mk19_bb_gm_s68_5",
"title":{
"__html":"Test Yourself"
},
"childHlIds":[
"7866cc",
"09eb6a",
"9f6f53"
]
}
],
"number":68
},
{
"id":"mk19_bb_gm_s69",
"title":{
"__html":"Scabies"
},
"childHlIds":[
"2d54eb"
],
"childSections":[
{
"id":"mk19_bb_gm_s69_1",
"title":{
"__html":"Diagnosis"
},
"childHlIds":[
"523223",
"589621",
"e4389a",
"2af4ae"
]
},
{
"id":"mk19_bb_gm_s69_2",
"title":{
"__html":"Testing"
},
"childHlIds":[
"fa6a5a",
"99fd3b",
"f5577f"
]
},
{
"id":"mk19_bb_gm_s69_3",
"title":{
"__html":"Treatment"
},
"childHlIds":[
"4c4ac0",
"0bf775",
"363ed5",
"b4fb5c",
"230a24",
"71a5e4"
]
},
{
"id":"mk19_bb_gm_s69_4",
"title":{
"__html":"Test Yourself"
},
"childHlIds":[
"7866cc",
"c6e552",
"61da7b"
]
}
],
"number":69
},
{
"id":"mk19_bb_gm_s70",
"title":{
"__html":"Bedbugs"
},
"childHlIds":[
"7baf98"
],
"childSections":[
{
"id":"mk19_bb_gm_s70_1",
"title":{
"__html":"Diagnosis"
},
"childHlIds":[
"523223",
"d5db01"
]
},
{
"id":"mk19_bb_gm_s70_2",
"title":{
"__html":"Treatment"
},
"childHlIds":[
"4c4ac0",
"c19fa6",
"ff1513"
]
}
],
"number":70
},
{
"id":"mk19_bb_gm_s71",
"title":{
"__html":"Seborrheic Keratosis"
},
"childHlIds":[
"b16b1d"
],
"childSections":[
{
"id":"mk19_bb_gm_s71_1",
"title":{
"__html":"Diagnosis"
},
"childHlIds":[
"523223",
"9a0c0f"
]
},
{
"id":"mk19_bb_gm_s71_2",
"title":{
"__html":"Treatment"
},
"childHlIds":[
"4c4ac0",
"3f1738",
"64f0db"
]
}
],
"number":71
},
{
"id":"mk19_bb_gm_s72",
"title":{
"__html":"Warts, Calluses, Corns, and Skin Tags"
},
"childHlIds":[
"264f69"
],
"childSections":[
{
"id":"mk19_bb_gm_s72_1",
"title":{
"__html":"Diagnosis"
},
"childHlIds":[
"523223",
"368861",
"158205",
"91357c"
]
},
{
"id":"mk19_bb_gm_s72_2",
"title":{
"__html":"Treatment"
},
"childHlIds":[
"4c4ac0",
"1027ee",
"a4a697",
"5d1287",
"3f0080"
]
}
],
"number":72
},
{
"id":"mk19_bb_gm_s73",
"title":{
"__html":"Dysplastic Nevi"
},
"childHlIds":[
"71d49a"
],
"childSections":[
{
"id":"mk19_bb_gm_s73_1",
"title":{
"__html":"Diagnosis"
},
"childHlIds":[
"523223",
"f64b04",
"8dbe3c",
"152a9f",
"9c306a",
"ecec0a",
"bc38db",
"0ca19d"
]
},
{
"id":"mk19_bb_gm_s73_2",
"title":{
"__html":"Treatment"
},
"childHlIds":[
"4c4ac0",
"a202f7"
]
}
],
"number":73
},
{
"id":"mk19_bb_gm_s74",
"title":{
"__html":"Actinic Keratosis"
},
"childHlIds":[
"f769db"
],
"childSections":[
{
"id":"mk19_bb_gm_s74_1",
"title":{
"__html":"Diagnosis"
},
"childHlIds":[
"523223",
"7bb8f6",
"e305e3"
]
},
{
"id":"mk19_bb_gm_s74_2",
"title":{
"__html":"Treatment"
},
"childHlIds":[
"4c4ac0",
"e2715a",
"032803"
]
}
],
"number":74
},
{
"id":"mk19_bb_gm_s75",
"title":{
"__html":"Squamous Cell Carcinoma"
},
"childHlIds":[
"357cf8"
],
"childSections":[
{
"id":"mk19_bb_gm_s75_1",
"title":{
"__html":"Diagnosis"
},
"childHlIds":[
"523223",
"b7bbb8",
"e1d338"
]
},
{
"id":"mk19_bb_gm_s75_2",
"title":{
"__html":"Treatment"
},
"childHlIds":[
"4c4ac0",
"ced64f",
"f5c4fd"
]
}
],
"number":75
},
{
"id":"mk19_bb_gm_s76",
"title":{
"__html":"Basal Cell Carcinoma"
},
"childHlIds":[
"737e02"
],
"childSections":[
{
"id":"mk19_bb_gm_s76_1",
"title":{
"__html":"Diagnosis"
},
"childHlIds":[
"523223",
"27a06c"
]
},
{
"id":"mk19_bb_gm_s76_2",
"title":{
"__html":"Treatment"
},
"childHlIds":[
"4c4ac0",
"5a0654",
"ebad5d"
]
}
],
"number":76
},
{
"id":"mk19_bb_gm_s77",
"title":{
"__html":"Melanoma"
},
"childHlIds":[
"ea6e07"
],
"childSections":[
{
"id":"mk19_bb_gm_s77_1",
"title":{
"__html":"Diagnosis"
},
"childHlIds":[
"523223",
"b516f6",
"777ed6",
"c1a91d",
"a66c2d",
"5748ce"
]
},
{
"id":"mk19_bb_gm_s77_2",
"title":{
"__html":"Treatment"
},
"childHlIds":[
"4c4ac0",
"42ae53",
"6e82e9"
]
}
],
"number":77
},
{
"id":"mk19_bb_gm_s78",
"title":{
"__html":"Other Papulosquamous Disorders"
},
"childHlIds":[
"11310f"
],
"childSections":[
{
"id":"mk19_bb_gm_s78_0",
"title":{
"__html":"Other Papulosquamous Disorders"
},
"childHlIds":[
"502de4"
]
}
],
"number":78
},
{
"id":"mk19_bb_gm_s79",
"title":{
"__html":"Psoriasis"
},
"childHlIds":[
"da0b68"
],
"childSections":[
{
"id":"mk19_bb_gm_s79_1",
"title":{
"__html":"Diagnosis"
},
"childHlIds":[
"523223",
"ba8251",
"f8f89f"
]
},
{
"id":"mk19_bb_gm_s79_2",
"title":{
"__html":"Treatment"
},
"childHlIds":[
"4c4ac0",
"0b783a",
"90ded1",
"2bce4f",
"8af971",
"b6e64f",
"f1bcb5",
"db1fa6",
"ded5b3",
"c31fce"
]
},
{
"id":"mk19_bb_gm_s79_3",
"title":{
"__html":"Test Yourself"
},
"childHlIds":[
"7866cc",
"62ac5d",
"6a8643"
]
}
],
"number":79
},
{
"id":"mk19_bb_gm_s80",
"title":{
"__html":"Erythema Multiforme"
},
"childHlIds":[
"9e23c4"
],
"childSections":[
{
"id":"mk19_bb_gm_s80_1",
"title":{
"__html":"Diagnosis"
},
"childHlIds":[
"523223",
"71225b",
"e12c9b"
]
},
{
"id":"mk19_bb_gm_s80_2",
"title":{
"__html":"Treatment"
},
"childHlIds":[
"4c4ac0",
"cd532f",
"c9e251",
"1b4721",
"b67ece",
"529be6"
]
},
{
"id":"mk19_bb_gm_s80_3",
"title":{
"__html":"Test Yourself"
},
"childHlIds":[
"7866cc",
"e47ff2",
"9f2e8c"
]
}
],
"number":80
},
{
"id":"mk19_bb_gm_s81",
"title":{
"__html":"Involuntary Weight Loss"
},
"childHlIds":[
"e7543a"
],
"childSections":[
{
"id":"mk19_bb_gm_s81_1",
"title":{
"__html":"Diagnosis"
},
"childHlIds":[
"523223",
"ff4af5",
"7f8fce",
"c4cc68"
]
},
{
"id":"mk19_bb_gm_s81_2",
"title":{
"__html":"Treatment"
},
"childHlIds":[
"4c4ac0",
"0cab7c",
"d41d8c"
]
}
],
"number":81
}
]