{
"id":"mk19_bb_id_f10",
"number":10,
"bookId":"id",
"legend":{
"type":"tag",
"tagName":"span",
"attrs":{
},
"children":[
"This enlarged image from a frontal chest x-ray shows a cavitary lesion (",
{
"type":"tag",
"tagName":"i",
"attrs":{
},
"children":[
"arrowheads"
]
},
") containing a round mass (",
{
"type":"tag",
"tagName":"i",
"attrs":{
},
"children":[
"arrow"
]
},
") representing a fungus ball."
]
},
"title":{
"type":"tag",
"tagName":"span",
"attrs":{
},
"children":[
"Aspergilloma:"
]
},
"footnotes":[

],
"imageInfo":{
"hash":"22338e5724f21afb0dc82e82fd50b0e3",
"height":1009,
"width":677,
"extension":"jpg"
}
}