{
"id":"mk19_b_pm_t63",
"number":63,
"bookId":"pm",
"title":{
"__html":"Causes of Severe Hyperthermia"
},
"jsonContent":{
"type":"tag",
"tagName":"table",
"attrs":{
"className":"table"
},
"children":[
{
"type":"tag",
"tagName":"caption",
"attrs":{
},
"children":[
{
"type":"p",
"hlId":"af1548",
"children":[
{
"type":"tag",
"tagName":"b",
"attrs":{
"className":"table-number"
},
"children":[
{
"type":"tag",
"tagName":"span",
"attrs":{
},
"children":[
"Table 63. "
]
},
{
"type":"new-window-link",
"targetType":"table",
"targetId":"mk19_b_pm_t63"
}
]
},
"Causes of Severe Hyperthermia"
]
}
]
},
{
"type":"tag",
"tagName":"thead",
"attrs":{
},
"children":[
{
"type":"tag",
"tagName":"tr",
"attrs":{
},
"children":[
{
"type":"tag",
"tagName":"th",
"attrs":{
"rowSpan":"1",
"colSpan":"1"
},
"children":[
" ",
{
"type":"p",
"hlId":"523223",
"class":"col hd l",
"children":[
"Diagnosis"
]
},
" "
]
},
{
"type":"tag",
"tagName":"th",
"attrs":{
"rowSpan":"1",
"colSpan":"1"
},
"children":[
" ",
{
"type":"p",
"hlId":"69c584",
"class":"col hd l",
"children":[
"Suggestive History"
]
},
" "
]
},
{
"type":"tag",
"tagName":"th",
"attrs":{
"rowSpan":"1",
"colSpan":"1"
},
"children":[
" ",
{
"type":"p",
"hlId":"8fccb8",
"class":"col hd l",
"children":[
"Key Examination Findings"
]
},
" "
]
},
{
"type":"tag",
"tagName":"th",
"attrs":{
"rowSpan":"1",
"colSpan":"1"
},
"children":[
" ",
{
"type":"p",
"hlId":"4c4ac0",
"class":"col hd l",
"children":[
"Treatment"
]
},
" "
]
},
{
"type":"tag",
"tagName":"th",
"attrs":{
"rowSpan":"1",
"colSpan":"1"
},
"children":[
" ",
{
"type":"p",
"hlId":"f4c6f8",
"class":"col hd l",
"children":[
"Notes"
]
},
" "
]
}
]
}
]
},
{
"type":"tag",
"tagName":"tbody",
"attrs":{
},
"children":[
{
"type":"tag",
"tagName":"tr",
"attrs":{
"className":"group_1-1 row-odd"
},
"children":[
{
"type":"tag",
"tagName":"td",
"attrs":{
"rowSpan":"1",
"colSpan":"1"
},
"children":[
" ",
{
"type":"p",
"hlId":"187677",
"class":"cell txt l",
"children":[
"Heat stroke"
]
},
" "
]
},
{
"type":"tag",
"tagName":"td",
"attrs":{
"rowSpan":"1",
"colSpan":"1"
},
"children":[
" ",
{
"type":"p",
"hlId":"34cb29",
"class":"cell txt l",
"children":[
"Environmental exposure"
]
},
" "
]
},
{
"type":"tag",
"tagName":"td",
"attrs":{
"rowSpan":"1",
"colSpan":"1"
},
"children":[
" ",
{
"type":"p",
"hlId":"3cfe39",
"class":"cell txt l",
"children":[
"Encephalopathy and fever"
]
},
" "
]
},
{
"type":"tag",
"tagName":"td",
"attrs":{
"rowSpan":"1",
"colSpan":"1"
},
"children":[
" ",
{
"type":"p",
"hlId":"1b2a47",
"class":"cell txt l",
"children":[
"Evaporative cooling"
]
},
" ",
{
"type":"p",
"hlId":"31560f",
"class":"cell txt l",
"children":[
"Ice water immersion"
]
},
" "
]
},
{
"type":"tag",
"tagName":"td",
"attrs":{
"rowSpan":"1",
"colSpan":"1"
},
"children":[
" ",
{
"type":"p",
"hlId":"e60bff",
"class":"cell txt l",
"children":[
"Avoid ice water immersion if nonexertional"
]
},
" "
]
}
]
},
{
"type":"tag",
"tagName":"tr",
"attrs":{
"className":"group_1-2 row-even"
},
"children":[
{
"type":"tag",
"tagName":"td",
"attrs":{
"rowSpan":"1",
"colSpan":"1"
},
"children":[
" ",
{
"type":"p",
"hlId":"e300b2",
"class":"cell txt l",
"children":[
"Malignant hyperthermia"
]
},
" "
]
},
{
"type":"tag",
"tagName":"td",
"attrs":{
"rowSpan":"1",
"colSpan":"1"
},
"children":[
" ",
{
"type":"p",
"hlId":"0b2df2",
"class":"cell txt l",
"children":[
"Exposure to volatile anesthetic or succinylcholine"
]
},
" "
]
},
{
"type":"tag",
"tagName":"td",
"attrs":{
"rowSpan":"1",
"colSpan":"1"
},
"children":[
" ",
{
"type":"p",
"hlId":"3882ba",
"class":"cell txt l",
"children":[
"Masseter muscle rigidity; ↑ arterial P",
{
"type":"tag",
"tagName":"small",
"attrs":{
},
"children":[
"CO"
]
},
{
"type":"tag",
"tagName":"sub",
"attrs":{
},
"children":[
"2"
]
}
]
},
" "
]
},
{
"type":"tag",
"tagName":"td",
"attrs":{
"rowSpan":"1",
"colSpan":"1"
},
"children":[
" ",
{
"type":"p",
"hlId":"f6bc74",
"class":"cell txt l",
"children":[
"Stop inciting drug"
]
},
" ",
{
"type":"p",
"hlId":"972ebf",
"class":"cell txt l",
"children":[
"Dantrolene"
]
},
" "
]
},
{
"type":"tag",
"tagName":"td",
"attrs":{
"rowSpan":"1",
"colSpan":"1"
},
"children":[
" ",
{
"type":"p",
"hlId":"ad595e",
"class":"cell txt l",
"children":[
"Monitor and treat ↑ K",
{
"type":"tag",
"tagName":"sup",
"attrs":{
},
"children":[
"+"
]
},
" and ↑ arterial P",
{
"type":"tag",
"tagName":"small",
"attrs":{
},
"children":[
"CO"
]
},
{
"type":"tag",
"tagName":"sub",
"attrs":{
},
"children":[
"2"
]
}
]
},
" "
]
}
]
},
{
"type":"tag",
"tagName":"tr",
"attrs":{
"className":"group_1-3 row-odd"
},
"children":[
{
"type":"tag",
"tagName":"td",
"attrs":{
"rowSpan":"1",
"colSpan":"1"
},
"children":[
" ",
{
"type":"p",
"hlId":"87fca9",
"class":"cell txt l",
"children":[
"Neuroleptic malignant syndrome"
]
},
" "
]
},
{
"type":"tag",
"tagName":"td",
"attrs":{
"rowSpan":"1",
"colSpan":"1"
},
"children":[
" ",
{
"type":"p",
"hlId":"2eb663",
"class":"cell txt l",
"children":[
"Typical > atypical antipsychotic agent; onset over days to weeks"
]
},
" "
]
},
{
"type":"tag",
"tagName":"td",
"attrs":{
"rowSpan":"1",
"colSpan":"1"
},
"children":[
" ",
{
"type":"p",
"hlId":"38c08b",
"class":"cell txt l",
"children":[
"Altered mentation, severe rigidity, ↑ HR, ↑ BP, hyporeflexia, no clonus"
]
},
" "
]
},
{
"type":"tag",
"tagName":"td",
"attrs":{
"rowSpan":"1",
"colSpan":"1"
},
"children":[
" ",
{
"type":"p",
"hlId":"f6bc74",
"class":"cell txt l",
"children":[
"Stop inciting drug"
]
},
" ",
{
"type":"p",
"hlId":"972ebf",
"class":"cell txt l",
"children":[
"Dantrolene"
]
},
" ",
{
"type":"p",
"hlId":"c7bf4f",
"class":"cell txt l",
"children":[
"Bromocriptine"
]
},
" "
]
},
{
"type":"tag",
"tagName":"td",
"attrs":{
"rowSpan":"1",
"colSpan":"1"
},
"children":[
" ",
{
"type":"p",
"hlId":"00f0b3",
"class":"cell txt l",
"children":[
"Resolves over days to weeks"
]
},
" ",
{
"type":"p",
"hlId":"d071c9",
"class":"cell txt l",
"children":[
"First symptom is usually change in mental status"
]
},
" "
]
}
]
},
{
"type":"tag",
"tagName":"tr",
"attrs":{
"className":"group_1-4 row-even"
},
"children":[
{
"type":"tag",
"tagName":"td",
"attrs":{
"rowSpan":"1",
"colSpan":"1"
},
"children":[
" ",
{
"type":"p",
"hlId":"9c06e8",
"class":"cell txt l",
"children":[
"Severe serotonin syndrome",
{
"type":"tag",
"tagName":"sup",
"attrs":{
},
"children":[
"a"
]
}
]
},
" "
]
},
{
"type":"tag",
"tagName":"td",
"attrs":{
"rowSpan":"1",
"colSpan":"1"
},
"children":[
" ",
{
"type":"p",
"hlId":"1516dc",
"class":"cell txt l",
"children":[
"Onset within 24 hours of initiation or increasing SSRI dose, gastrointestinal prodrome"
]
},
" "
]
},
{
"type":"tag",
"tagName":"td",
"attrs":{
"rowSpan":"1",
"colSpan":"1"
},
"children":[
" ",
{
"type":"p",
"hlId":"d089ce",
"class":"cell txt l",
"children":[
"Agitation, myoclonus, ↑ reflexes, rigidity"
]
},
" "
]
},
{
"type":"tag",
"tagName":"td",
"attrs":{
"rowSpan":"1",
"colSpan":"1"
},
"children":[
" ",
{
"type":"p",
"hlId":"f6bc74",
"class":"cell txt l",
"children":[
"Stop inciting drug"
]
},
" ",
{
"type":"p",
"hlId":"521c0d",
"class":"cell txt l",
"children":[
"Benzodiazepines"
]
},
" ",
{
"type":"p",
"hlId":"f27c7c",
"class":"cell txt l",
"children":[
"Cyproheptadine"
]
},
" "
]
},
{
"type":"tag",
"tagName":"td",
"attrs":{
"rowSpan":"1",
"colSpan":"1"
},
"children":[
" ",
{
"type":"p",
"hlId":"66c47e",
"class":"cell txt l",
"children":[
"Resolves in 24 hours"
]
},
" "
]
}
]
}
]
}
]
},
"footnotes":[
[
"BP = blood pressure; HR = heart rate; K",
{
"type":"tag",
"tagName":"sup",
"attrs":{
},
"children":[
"+"
]
},
" = potassium; SSRI = selective serotonin reuptake inhibitor."
],
[
{
"type":"tag",
"tagName":"sup",
"attrs":{
},
"children":[
"a"
]
},
"Not routinely considered a cause of severe hyperthermia but commonly confused with neuroleptic malignant syndrome."
]
]
}