{
"id":"mk19_b_gm_t05",
"number":5,
"bookId":"gm2",
"title":{
"__html":"Screening for Infectious Diseases in High-Risk Populations"
},
"jsonContent":{
"type":"tag",
"tagName":"table",
"attrs":{
"className":"table"
},
"children":[
{
"type":"tag",
"tagName":"caption",
"attrs":{
},
"children":[
{
"type":"p",
"hlId":"68f087",
"children":[
{
"type":"tag",
"tagName":"b",
"attrs":{
"className":"table-number"
},
"children":[
{
"type":"tag",
"tagName":"span",
"attrs":{
},
"children":[
"Table 5. "
]
},
{
"type":"new-window-link",
"targetType":"table",
"targetId":"mk19_b_gm_t05"
}
]
},
"Screening for Infectious Diseases in High-Risk Populations"
]
}
]
},
{
"type":"tag",
"tagName":"thead",
"attrs":{
},
"children":[
{
"type":"tag",
"tagName":"tr",
"attrs":{
},
"children":[
{
"type":"tag",
"tagName":"th",
"attrs":{
"rowSpan":"1",
"colSpan":"1"
},
"children":[
" ",
{
"type":"p",
"hlId":"1c23de",
"class":"col hd l",
"children":[
"Specific Populations"
]
},
" "
]
},
{
"type":"tag",
"tagName":"th",
"attrs":{
"rowSpan":"1",
"colSpan":"1"
},
"children":[
" ",
{
"type":"p",
"hlId":"a1d5b5",
"class":"col hd l",
"children":[
"Recommended Screening"
]
},
" "
]
}
]
}
]
},
{
"type":"tag",
"tagName":"tbody",
"attrs":{
},
"children":[
{
"type":"tag",
"tagName":"tr",
"attrs":{
"className":"group_1-1 row-odd"
},
"children":[
{
"type":"tag",
"tagName":"td",
"attrs":{
"rowSpan":"1",
"colSpan":"1"
},
"children":[
" ",
{
"type":"p",
"hlId":"56d4b1",
"class":"cell txt l",
"children":[
"Pregnant women"
]
},
" "
]
},
{
"type":"tag",
"tagName":"td",
"attrs":{
"rowSpan":"1",
"colSpan":"1"
},
"children":[
" ",
{
"type":"p",
"hlId":"ca5976",
"class":"cell txt l",
"children":[
"Chlamydia and gonorrhea, hepatitis B, HIV, syphilis, asymptomatic bacteriuria"
]
},
" "
]
}
]
},
{
"type":"tag",
"tagName":"tr",
"attrs":{
"className":"group_1-2 row-even"
},
"children":[
{
"type":"tag",
"tagName":"td",
"attrs":{
"rowSpan":"1",
"colSpan":"1"
},
"children":[
" ",
{
"type":"p",
"hlId":"986876",
"class":"cell txt l",
"children":[
"Persons engaging in high-risk sexual behavior"
]
},
" "
]
},
{
"type":"tag",
"tagName":"td",
"attrs":{
"rowSpan":"1",
"colSpan":"1"
},
"children":[
" ",
{
"type":"p",
"hlId":"e3cff5",
"class":"cell txt l",
"children":[
"Hepatitis B and C, HIV, syphilis"
]
},
" "
]
}
]
},
{
"type":"tag",
"tagName":"tr",
"attrs":{
"className":"group_1-3 row-odd"
},
"children":[
{
"type":"tag",
"tagName":"td",
"attrs":{
"rowSpan":"1",
"colSpan":"1"
},
"children":[
" ",
{
"type":"p",
"hlId":"d5e9ca",
"class":"cell txt l",
"children":[
"Men who have sex with men"
]
},
" "
]
},
{
"type":"tag",
"tagName":"td",
"attrs":{
"rowSpan":"1",
"colSpan":"1"
},
"children":[
" ",
{
"type":"p",
"hlId":"7f4c6c",
"class":"cell txt l",
"children":[
"Chlamydia and gonorrhea, hepatitis B, HIV, syphilis"
]
},
" "
]
}
]
},
{
"type":"tag",
"tagName":"tr",
"attrs":{
"className":"group_1-4 row-even"
},
"children":[
{
"type":"tag",
"tagName":"td",
"attrs":{
"rowSpan":"1",
"colSpan":"1"
},
"children":[
" ",
{
"type":"p",
"hlId":"068fc3",
"class":"cell txt l",
"children":[
"Injection drug users"
]
},
" "
]
},
{
"type":"tag",
"tagName":"td",
"attrs":{
"rowSpan":"1",
"colSpan":"1"
},
"children":[
" ",
{
"type":"p",
"hlId":"749232",
"class":"cell txt l",
"children":[
"Hepatitis B and C, HIV"
]
},
" "
]
}
]
},
{
"type":"tag",
"tagName":"tr",
"attrs":{
"className":"group_1-5 row-odd"
},
"children":[
{
"type":"tag",
"tagName":"td",
"attrs":{
"rowSpan":"1",
"colSpan":"1"
},
"children":[
" ",
{
"type":"p",
"hlId":"373220",
"class":"cell txt l",
"children":[
"Prisoners"
]
},
" "
]
},
{
"type":"tag",
"tagName":"td",
"attrs":{
"rowSpan":"1",
"colSpan":"1"
},
"children":[
" ",
{
"type":"p",
"hlId":"46f8dd",
"class":"cell txt l",
"children":[
"Hepatitis C, hepatitis B",
{
"type":"tag",
"tagName":"sup",
"attrs":{
},
"children":[
"a"
]
},
", syphilis, tuberculosis"
]
},
" "
]
}
]
},
{
"type":"tag",
"tagName":"tr",
"attrs":{
"className":"group_1-6 row-even"
},
"children":[
{
"type":"tag",
"tagName":"td",
"attrs":{
"rowSpan":"1",
"colSpan":"1"
},
"children":[
" ",
{
"type":"p",
"hlId":"5bb49a",
"class":"cell txt l",
"children":[
"Persons receiving hemodialysis"
]
},
" "
]
},
{
"type":"tag",
"tagName":"td",
"attrs":{
"rowSpan":"1",
"colSpan":"1"
},
"children":[
" ",
{
"type":"p",
"hlId":"5654f8",
"class":"cell txt l",
"children":[
"Hepatitis B",
{
"type":"tag",
"tagName":"sup",
"attrs":{
},
"children":[
"a"
]
},
" and C, tuberculosis"
]
},
" "
]
}
]
},
{
"type":"tag",
"tagName":"tr",
"attrs":{
"className":"group_1-7 row-odd"
},
"children":[
{
"type":"tag",
"tagName":"td",
"attrs":{
"rowSpan":"1",
"colSpan":"1"
},
"children":[
" ",
{
"type":"p",
"hlId":"2f1168",
"class":"cell txt l",
"children":[
"Persons born in or living in countries with ≥2% hepatitis B virus prevalence",
{
"type":"tag",
"tagName":"sup",
"attrs":{
},
"children":[
"b"
]
}
]
},
" "
]
},
{
"type":"tag",
"tagName":"td",
"attrs":{
"rowSpan":"1",
"colSpan":"1"
},
"children":[
" ",
{
"type":"p",
"hlId":"7f96a2",
"class":"cell txt l",
"children":[
"Hepatitis B and tuberculosis depending on prevalence of disease"
]
},
" "
]
}
]
},
{
"type":"tag",
"tagName":"tr",
"attrs":{
"className":"group_1-8 row-even"
},
"children":[
{
"type":"tag",
"tagName":"td",
"attrs":{
"rowSpan":"1",
"colSpan":"1"
},
"children":[
" ",
{
"type":"p",
"hlId":"4f450c",
"class":"cell txt l",
"children":[
"Health care workers"
]
},
" "
]
},
{
"type":"tag",
"tagName":"td",
"attrs":{
"rowSpan":"1",
"colSpan":"1"
},
"children":[
" ",
{
"type":"p",
"hlId":"01e5a1",
"class":"cell txt l",
"children":[
"Tuberculosis (baseline testing only); pre-employment verification of immunity to hepatitis B virus, measles, mumps, rubella, and varicella"
]
},
" "
]
}
]
}
]
}
]
},
"footnotes":[
[
{
"type":"tag",
"tagName":"sup",
"attrs":{
},
"children":[
"a"
]
},
"Recommendations from the Centers for Disease Control and Prevention."
],
[
{
"type":"tag",
"tagName":"sup",
"attrs":{
},
"children":[
"b"
]
},
"Including most of sub-Saharan Africa, central and southeast Asia, and parts of South America. See ",
{
"type":"tag",
"tagName":"a",
"attrs":{
"href":"https://wwwnc.cdc.gov/travel/yellowbook/2020/travel-related-infectious-diseases/hepatitis-b",
"target":"_blank"
},
"children":[
"https://wwwnc.cdc.gov/travel/yellowbook/2020/travel-related-infectious-diseases/hepatitis-b"
]
},
" for further details."
]
]
}