{
"id":"mk19_b_gm_t54",
"number":54,
"bookId":"gm2",
"title":{
"__html":"Clinical Presentation, Evaluation, and Management of Vaginitis"
},
"jsonContent":{
"type":"tag",
"tagName":"table",
"attrs":{
"className":"table"
},
"children":[
{
"type":"tag",
"tagName":"caption",
"attrs":{
},
"children":[
{
"type":"p",
"hlId":"eaa389",
"children":[
{
"type":"tag",
"tagName":"b",
"attrs":{
"className":"table-number"
},
"children":[
{
"type":"tag",
"tagName":"span",
"attrs":{
},
"children":[
"Table 54. "
]
},
{
"type":"new-window-link",
"targetType":"table",
"targetId":"mk19_b_gm_t54"
}
]
},
"Clinical Presentation, Evaluation, and Management of Vaginitis"
]
}
]
},
{
"type":"tag",
"tagName":"thead",
"attrs":{
},
"children":[
{
"type":"tag",
"tagName":"tr",
"attrs":{
},
"children":[
{
"type":"tag",
"tagName":"th",
"attrs":{
"rowSpan":"1",
"colSpan":"1"
},
"children":[
" ",
{
"type":"p",
"hlId":"4cd473",
"class":"col hd l",
"children":[
"Cause of Vaginitis"
]
},
" "
]
},
{
"type":"tag",
"tagName":"th",
"attrs":{
"rowSpan":"1",
"colSpan":"1"
},
"children":[
" ",
{
"type":"p",
"hlId":"6f071b",
"class":"col hd l",
"children":[
"Clinical Presentation"
]
},
" "
]
},
{
"type":"tag",
"tagName":"th",
"attrs":{
"rowSpan":"1",
"colSpan":"1"
},
"children":[
" ",
{
"type":"p",
"hlId":"b74a43",
"class":"col hd l",
"children":[
"Evaluation"
]
},
" "
]
},
{
"type":"tag",
"tagName":"th",
"attrs":{
"rowSpan":"1",
"colSpan":"1"
},
"children":[
" ",
{
"type":"p",
"hlId":"fe4dbc",
"class":"col hd l",
"children":[
"Management"
]
},
" "
]
}
]
}
]
},
{
"type":"tag",
"tagName":"tbody",
"attrs":{
},
"children":[
{
"type":"tag",
"tagName":"tr",
"attrs":{
"className":"group_1-1 row-odd"
},
"children":[
{
"type":"tag",
"tagName":"td",
"attrs":{
"rowSpan":"1",
"colSpan":"1"
},
"children":[
" ",
{
"type":"p",
"hlId":"4ab36a",
"class":"cell txt l",
"children":[
"Bacterial vaginosis"
]
},
" "
]
},
{
"type":"tag",
"tagName":"td",
"attrs":{
"rowSpan":"1",
"colSpan":"1"
},
"children":[
" ",
{
"type":"p",
"hlId":"24125a",
"class":"cell txt l",
"children":[
"Malodorous or “fishy” vaginal discharge"
]
},
" ",
{
"type":"p",
"hlId":"52b8f6",
"class":"cell txt l",
"children":[
"Increased thin white or gray discharge"
]
},
" ",
{
"type":"p",
"hlId":"daeb99",
"class":"cell txt l",
"children":[
"Symptoms other than malodor may be minimal"
]
},
" "
]
},
{
"type":"tag",
"tagName":"td",
"attrs":{
"rowSpan":"1",
"colSpan":"1"
},
"children":[
" ",
{
"type":"p",
"hlId":"b778de",
"class":"cell txt l",
"children":[
"Diagnosis requires three of four findings (Amsel criteria):"
]
},
" ",
{
"type":"p",
"hlId":"43db8c",
"class":"cell txt li",
"children":[
"pH >4.5"
]
},
" ",
{
"type":"p",
"hlId":"798bac",
"class":"cell txt li",
"children":[
"Thin homogenous discharge"
]
},
" ",
{
"type":"p",
"hlId":"3b99a3",
"class":"cell txt li",
"children":[
"KOH amine whiff test result positive"
]
},
" ",
{
"type":"p",
"hlId":"ac4de0",
"class":"cell txt li",
"children":[
"Saline wet mount with >20% epithelial clue cells"
]
},
" "
]
},
{
"type":"tag",
"tagName":"td",
"attrs":{
"rowSpan":"1",
"colSpan":"1"
},
"children":[
" ",
{
"type":"p",
"hlId":"4edbc4",
"class":"cell txt l",
"children":[
"Metronidazole: 500 mg orally twice daily for 7 days",
{
"type":"tag",
"tagName":"sup",
"attrs":{
},
"children":[
"a"
]
},
" (avoid alcohol during treatment and for 24 hours after last dose); or vaginal gel (0.75%) 5 g into vagina at bedtime for 5 nights"
]
},
" ",
{
"type":"p",
"hlId":"6d0234",
"class":"cell txt l",
"children":[
"Clindamycin: vaginal cream (2%) 5 g into vagina for 7 nights"
]
},
" ",
{
"type":"p",
"hlId":"c2d098",
"class":"cell txt l",
"children":[
"Sexual partners do not require treatment"
]
},
" ",
{
"type":"p",
"hlId":"de5bdb",
"class":"cell txt l",
"children":[
"Avoid sexual activity (or use condoms) during treatment"
]
},
" "
]
}
]
},
{
"type":"tag",
"tagName":"tr",
"attrs":{
"className":"group_1-2 row-even"
},
"children":[
{
"type":"tag",
"tagName":"td",
"attrs":{
"rowSpan":"1",
"colSpan":"1"
},
"children":[
" ",
{
"type":"p",
"hlId":"8bf376",
"class":"cell txt l",
"children":[
"Vulvovaginal candidiasis"
]
},
" "
]
},
{
"type":"tag",
"tagName":"td",
"attrs":{
"rowSpan":"1",
"colSpan":"1"
},
"children":[
" ",
{
"type":"p",
"hlId":"a813d8",
"class":"cell txt l",
"children":[
"Itching, irritation, dysuria, dyspareunia, vulvodynia, excoriation, erythema, fissures"
]
},
" ",
{
"type":"p",
"hlId":"47ed8b",
"class":"cell txt l",
"children":[
"Increased thick white discharge"
]
},
" "
]
},
{
"type":"tag",
"tagName":"td",
"attrs":{
"rowSpan":"1",
"colSpan":"1"
},
"children":[
" ",
{
"type":"p",
"hlId":"cd8a2f",
"class":"cell txt l",
"children":[
"pH ≤4.5"
]
},
" ",
{
"type":"p",
"hlId":"5de09a",
"class":"cell txt l",
"children":[
"KOH amine whiff test result negative"
]
},
" ",
{
"type":"p",
"hlId":"0c6579",
"class":"cell txt l",
"children":[
"KOH wet mount shows hyphae, pseudohyphae, or yeast"
]
},
" "
]
},
{
"type":"tag",
"tagName":"td",
"attrs":{
"rowSpan":"1",
"colSpan":"1"
},
"children":[
" ",
{
"type":"p",
"hlId":"2fd931",
"class":"cell txt l",
"children":[
" ",
{
"type":"tag",
"tagName":"b",
"attrs":{
},
"children":[
"Uncomplicated",
{
"type":"tag",
"tagName":"sup",
"attrs":{
},
"children":[
"b"
]
}
]
},
" "
]
},
" ",
{
"type":"p",
"hlId":"6e96f9",
"class":"cell txt l",
"children":[
" ",
{
"type":"tag",
"tagName":"b",
"attrs":{
},
"children":[
"Over-the-Counter Intravaginal Agents"
]
},
" "
]
},
" ",
{
"type":"p",
"hlId":"44dd44",
"class":"cell txt l",
"children":[
"Clotrimazole: 1% cream 5 g intravaginally daily for 7–14 days; or 2% cream 5 g intravaginally daily for 3 days"
]
},
" ",
{
"type":"p",
"hlId":"ecba29",
"class":"cell txt l",
"children":[
"Miconazole: 2% cream 5 g intravaginally daily for 7 days; or 4% cream 5 g intravaginally daily for 3 days; or 100-mg vaginal suppository, one suppository daily for 7 days; or 200-mg vaginal suppository, one suppository for 3 days; or 1,200- mg vaginal suppository, one suppository for 1 day"
]
},
" ",
{
"type":"p",
"hlId":"c4eedf",
"class":"cell txt l",
"children":[
"Tioconazole: 6.5% ointment 5 g intravaginally in a single application"
]
},
" ",
{
"type":"p",
"hlId":"8193a5",
"class":"cell txt l",
"children":[
" ",
{
"type":"tag",
"tagName":"b",
"attrs":{
},
"children":[
"Prescription Intravaginal Agents"
]
},
" "
]
},
" ",
{
"type":"p",
"hlId":"4ec40b",
"class":"cell txt l",
"children":[
"Butoconazole: 2% cream (single-dose bioadhesive product) 5 g intravaginally in a single application"
]
},
" ",
{
"type":"p",
"hlId":"7ec62e",
"class":"cell txt l",
"children":[
"Terconazole: 0.4% cream 5 g intravaginally daily for 7 days; or 0.8% cream 5 g intravaginally daily for 3 days; or 80-mg vaginal suppository, one suppository daily for 3 days"
]
},
" ",
{
"type":"p",
"hlId":"ed9663",
"class":"cell txt l",
"children":[
" ",
{
"type":"tag",
"tagName":"b",
"attrs":{
},
"children":[
"Prescription Oral Agent"
]
},
" "
]
},
" ",
{
"type":"p",
"hlId":"ca8911",
"class":"cell txt l",
"children":[
"Fluconazole: 150 mg orally as a single dose"
]
},
" ",
{
"type":"p",
"hlId":"103d0b",
"class":"cell txt l",
"children":[
" ",
{
"type":"tag",
"tagName":"b",
"attrs":{
},
"children":[
"Complicated",
{
"type":"tag",
"tagName":"sup",
"attrs":{
},
"children":[
"c"
]
}
]
},
" "
]
},
" ",
{
"type":"p",
"hlId":"ca8c85",
"class":"cell txt l",
"children":[
"Longer duration of initial oral or topical treatment, followed by maintenance therapy as needed:"
]
},
" ",
{
"type":"p",
"hlId":"617da6",
"class":"cell txt li",
"children":[
"Recurrent:"
]
},
" ",
{
"type":"p",
"hlId":"fa45c2",
"class":"cell txt lii",
"children":[
"Fluconazole: 150 mg orally every 3 days for a total of three doses; or topical imidazole therapy for 7-14 nights"
]
},
" ",
{
"type":"p",
"hlId":"67a3ba",
"class":"cell txt lii",
"children":[
"Maintenance therapy for refractory or recurrent symptoms:"
]
},
" ",
{
"type":"p",
"hlId":"fe4586",
"class":"cell txt lii",
"children":[
"Fluconazole: 150 mg orally weekly for 6 months"
]
},
" ",
{
"type":"p",
"hlId":"0bf52d",
"class":"cell txt li",
"children":[
"Severe:"
]
},
" ",
{
"type":"p",
"hlId":"225dd7",
"class":"cell txt lii",
"children":[
"Topical azole for 7-14 days or fluconazole 150mg for two doses separated by 72 hours"
]
},
" ",
{
"type":"p",
"hlId":"74477c",
"class":"cell txt li",
"children":[
"Non-albicans species:"
]
},
" ",
{
"type":"p",
"hlId":"517560",
"class":"cell txt lii",
"children":[
"Non-fluconazole topical azole for 7-14 days"
]
},
" ",
{
"type":"p",
"hlId":"cf424f",
"class":"cell txt l",
"children":[
"Pregnancy:"
]
},
" ",
{
"type":"p",
"hlId":"3a545d",
"class":"cell txt li",
"children":[
"Topical azole for 7 days; do not use fluconazole"
]
},
" ",
{
"type":"p",
"hlId":"c2d098",
"class":"cell txt l",
"children":[
"Sexual partners do not require treatment"
]
},
" "
]
}
]
},
{
"type":"tag",
"tagName":"tr",
"attrs":{
"className":"group_1-3 row-odd"
},
"children":[
{
"type":"tag",
"tagName":"td",
"attrs":{
"rowSpan":"1",
"colSpan":"1"
},
"children":[
" ",
{
"type":"p",
"hlId":"44f3ef",
"class":"cell txt l",
"children":[
"Trichomoniasis"
]
},
" "
]
},
{
"type":"tag",
"tagName":"td",
"attrs":{
"rowSpan":"1",
"colSpan":"1"
},
"children":[
" ",
{
"type":"p",
"hlId":"53b447",
"class":"cell txt l",
"children":[
"Increased discolored discharge (yellowish, green, gray, and/or frothy)"
]
},
" ",
{
"type":"p",
"hlId":"5aeade",
"class":"cell txt l",
"children":[
"Dyspareunia, dysuria, itch, erythema, postcoital bleeding"
]
},
" ",
{
"type":"p",
"hlId":"c2744a",
"class":"cell txt l",
"children":[
"Punctate cervical hemorrhages (“strawberry” cervix)"
]
},
" "
]
},
{
"type":"tag",
"tagName":"td",
"attrs":{
"rowSpan":"1",
"colSpan":"1"
},
"children":[
" ",
{
"type":"p",
"hlId":"5de09a",
"class":"cell txt l",
"children":[
"KOH amine whiff test result negative"
]
},
" ",
{
"type":"p",
"hlId":"370c4c",
"class":"cell txt l",
"children":[
"Saline wet mount with trichomonads, leukocytes"
]
},
" ",
{
"type":"p",
"hlId":"375280",
"class":"cell txt l",
"children":[
"NAAT or rapid assay result positive"
]
},
" "
]
},
{
"type":"tag",
"tagName":"td",
"attrs":{
"rowSpan":"1",
"colSpan":"1"
},
"children":[
" ",
{
"type":"p",
"hlId":"e1cc00",
"class":"cell txt l",
"children":[
"Metronidazole",
{
"type":"tag",
"tagName":"sup",
"attrs":{
},
"children":[
"a"
]
},
": 500 mg orally twice daily for 7 days"
]
},
" ",
{
"type":"p",
"hlId":"e9bd57",
"class":"cell txt l",
"children":[
"Treatment of sexual partners is recommended to prevent reinfection; for men, metronidazole 2 g orally as a single dose"
]
},
" "
]
}
]
}
]
}
]
},
"footnotes":[
[
"KOH = potassium hydroxide; NAAT = nucleic acid amplification test."
],
[
{
"type":"tag",
"tagName":"sup",
"attrs":{
},
"children":[
"a"
]
},
"Safe in pregnancy."
],
[
{
"type":"tag",
"tagName":"sup",
"attrs":{
},
"children":[
"b"
]
},
"Uncomplicated vulvovaginal candidiasis: ",
{
"type":"tag",
"tagName":"i",
"attrs":{
},
"children":[
"Candida albicans"
]
},
", mild to moderate symptom severity, healthy nonpregnant women, one or two episodes per year."
],
[
{
"type":"tag",
"tagName":"sup",
"attrs":{
},
"children":[
"c"
]
},
"Complicated vulvovaginal candidiasis: Recurrent (three or more episodes per year), severe symptoms, suspected or proven non-albicans ",
{
"type":"tag",
"tagName":"i",
"attrs":{
},
"children":[
"Candida"
]
},
" species, uncontrolled diabetes mellitus, or immunosuppression."
],
[
"Treatment regimens from the CDC Sexually Transmitted Infections Guidelines, 2021."
]
]
}