{
"id":"mk19_b_rm_t38",
"number":38,
"bookId":"rm",
"title":{
"__html":"Causes of Secondary Vasculitis"
},
"jsonContent":{
"type":"tag",
"tagName":"table",
"attrs":{
"className":"table"
},
"children":[
{
"type":"tag",
"tagName":"caption",
"attrs":{
},
"children":[
{
"type":"p",
"hlId":"bd6542",
"children":[
{
"type":"tag",
"tagName":"b",
"attrs":{
"className":"table-number"
},
"children":[
{
"type":"tag",
"tagName":"span",
"attrs":{
},
"children":[
"Table 38. "
]
},
{
"type":"new-window-link",
"targetType":"table",
"targetId":"mk19_b_rm_t38"
}
]
},
"Causes of Secondary Vasculitis"
]
}
]
},
{
"type":"tag",
"tagName":"thead",
"attrs":{
},
"children":[
{
"type":"tag",
"tagName":"tr",
"attrs":{
},
"children":[
{
"type":"tag",
"tagName":"th",
"attrs":{
"rowSpan":"1",
"colSpan":"1"
},
"children":[
" ",
{
"type":"p",
"hlId":"ba25cf",
"class":"col hd l",
"children":[
"Medications"
]
},
" "
]
}
]
}
]
},
{
"type":"tag",
"tagName":"tbody",
"attrs":{
},
"children":[
{
"type":"tag",
"tagName":"tr",
"attrs":{
},
"children":[
{
"type":"tag",
"tagName":"td",
"attrs":{
"rowSpan":"1",
"colSpan":"1"
},
"children":[
" ",
{
"type":"p",
"hlId":"b1c27f",
"class":"cell txt l",
"children":[
"Common causes: antimicrobial agents (e.g., minocycline, sulfadiazine); antithyroid agents (propylthiouracil [80%-90%], methimazole, carbimazole, benzylthiouracil [10%-20%; not available in the United States]); cardiovascular drugs (hydralazine); tumor necrosis factor inhibitors"
]
},
" ",
{
"type":"p",
"hlId":"4d9592",
"class":"cell txt l",
"children":[
"Rare causes: vaccines; antiepileptic agents; antiarrhythmic agents; diuretics; anticoagulants; antineoplastic agents; hematopoietic growth factors; NSAIDs; psychotropic drugs; sympathomimetic agents; allopurinol; interferon alfa; levamisole (associated with cocaine)"
]
},
" "
]
}
]
},
{
"type":"tag",
"tagName":"tr",
"attrs":{
},
"children":[
{
"type":"tag",
"tagName":"th",
"attrs":{
"rowSpan":"1",
"colSpan":"1"
},
"children":[
" ",
{
"type":"p",
"hlId":"2c194f",
"class":"col hd l",
"children":[
"Infections"
]
},
" "
]
}
]
},
{
"type":"tag",
"tagName":"tr",
"attrs":{
},
"children":[
{
"type":"tag",
"tagName":"td",
"attrs":{
"rowSpan":"1",
"colSpan":"1"
},
"children":[
" ",
{
"type":"p",
"hlId":"31cd4c",
"class":"cell txt l",
"children":[
"Hepatitis A, B, and C viruses; HIV; bacterial endocarditis; parvovirus B19"
]
},
" "
]
}
]
},
{
"type":"tag",
"tagName":"tr",
"attrs":{
},
"children":[
{
"type":"tag",
"tagName":"th",
"attrs":{
"rowSpan":"1",
"colSpan":"1"
},
"children":[
" ",
{
"type":"p",
"hlId":"4d0302",
"class":"col hd l",
"children":[
"Neoplasms"
]
},
" "
]
}
]
},
{
"type":"tag",
"tagName":"tr",
"attrs":{
},
"children":[
{
"type":"tag",
"tagName":"td",
"attrs":{
"rowSpan":"1",
"colSpan":"1"
},
"children":[
" ",
{
"type":"p",
"hlId":"e0d866",
"class":"cell txt l",
"children":[
"Hairy cell leukemia (associated with polyarteritis nodosa); other hematologic and solid malignancies"
]
},
" "
]
}
]
},
{
"type":"tag",
"tagName":"tr",
"attrs":{
},
"children":[
{
"type":"tag",
"tagName":"th",
"attrs":{
"rowSpan":"1",
"colSpan":"1"
},
"children":[
" ",
{
"type":"p",
"hlId":"9f4f09",
"class":"col hd l",
"children":[
"Autoimmune Diseases"
]
},
" "
]
}
]
},
{
"type":"tag",
"tagName":"tr",
"attrs":{
},
"children":[
{
"type":"tag",
"tagName":"td",
"attrs":{
"rowSpan":"1",
"colSpan":"1"
},
"children":[
" ",
{
"type":"p",
"hlId":"52543c",
"class":"cell txt l",
"children":[
"Systemic lupus erythematosus; rheumatoid arthritis; Sjögren syndrome; inflammatory myopathies; systemic sclerosis; relapsing polychondritis; inflammatory bowel disease; primary biliary cirrhosis"
]
},
" "
]
}
]
}
]
}
]
},
"footnotes":[

]
}