{
"id":"mk19_a_nr_t21",
"number":21,
"bookId":"nr",
"title":{
"__html":"Adverse Effects of Selected Antiepileptic Drugs and Recommended Laboratory Monitoring"
},
"jsonContent":{
"type":"tag",
"tagName":"table",
"attrs":{
"className":"table"
},
"children":[
{
"type":"tag",
"tagName":"caption",
"attrs":{
},
"children":[
{
"type":"p",
"hlId":"0cbfc6",
"children":[
{
"type":"tag",
"tagName":"b",
"attrs":{
"className":"table-number"
},
"children":[
{
"type":"tag",
"tagName":"span",
"attrs":{
},
"children":[
"Table 21. "
]
},
{
"type":"new-window-link",
"targetType":"table",
"targetId":"mk19_a_nr_t21"
}
]
},
"Adverse Effects of Selected Antiepileptic Drugs and Recommended Laboratory Monitoring"
]
}
]
},
{
"type":"tag",
"tagName":"thead",
"attrs":{
},
"children":[
{
"type":"tag",
"tagName":"tr",
"attrs":{
},
"children":[
{
"type":"tag",
"tagName":"th",
"attrs":{
"rowSpan":"1",
"colSpan":"1"
},
"children":[
" ",
{
"type":"p",
"hlId":"5db77f",
"class":"col hd l",
"children":[
"Drug"
]
},
" "
]
},
{
"type":"tag",
"tagName":"th",
"attrs":{
"rowSpan":"1",
"colSpan":"1"
},
"children":[
" ",
{
"type":"p",
"hlId":"3251b0",
"class":"col hd l",
"children":[
"Common Adverse Effects"
]
},
" "
]
},
{
"type":"tag",
"tagName":"th",
"attrs":{
"rowSpan":"1",
"colSpan":"1"
},
"children":[
" ",
{
"type":"p",
"hlId":"6d4ad7",
"class":"col hd l",
"children":[
"Serious Adverse Effects"
]
},
" "
]
},
{
"type":"tag",
"tagName":"th",
"attrs":{
"rowSpan":"1",
"colSpan":"1"
},
"children":[
" ",
{
"type":"p",
"hlId":"91e9ce",
"class":"col hd l",
"children":[
"Recommended Laboratory Monitoring"
]
},
" "
]
}
]
}
]
},
{
"type":"tag",
"tagName":"tbody",
"attrs":{
},
"children":[
{
"type":"tag",
"tagName":"tr",
"attrs":{
"className":"group_1-1 row-odd"
},
"children":[
{
"type":"tag",
"tagName":"td",
"attrs":{
"rowSpan":"1",
"colSpan":"1"
},
"children":[
" ",
{
"type":"p",
"hlId":"85b0f7",
"class":"cell txt l",
"children":[
"Carbamazepine, oxcarbazepine, and eslicarbazepine"
]
},
" "
]
},
{
"type":"tag",
"tagName":"td",
"attrs":{
"rowSpan":"1",
"colSpan":"1"
},
"children":[
" ",
{
"type":"p",
"hlId":"a97305",
"class":"cell txt l",
"children":[
"Sedation, nausea, ataxia, tremor, diplopia, imbalance, headache, and dose-dependent dizziness"
]
},
" "
]
},
{
"type":"tag",
"tagName":"td",
"attrs":{
"rowSpan":"1",
"colSpan":"1"
},
"children":[
" ",
{
"type":"p",
"hlId":"6ab8c0",
"class":"cell txt l",
"children":[
"Hyponatremia, rash, pancytopenia, osteoporosis, hepatotoxicity"
]
},
" "
]
},
{
"type":"tag",
"tagName":"td",
"attrs":{
"rowSpan":"1",
"colSpan":"1"
},
"children":[
" ",
{
"type":"p",
"hlId":"535d9f",
"class":"cell txt l",
"children":[
"CBC, liver chemistry studies, bone density, serum drug level"
]
},
" "
]
}
]
},
{
"type":"tag",
"tagName":"tr",
"attrs":{
"className":"group_1-2 row-even"
},
"children":[
{
"type":"tag",
"tagName":"td",
"attrs":{
"rowSpan":"1",
"colSpan":"1"
},
"children":[
" ",
{
"type":"p",
"hlId":"c90a25",
"class":"cell txt l",
"children":[
"Felbamate"
]
},
" "
]
},
{
"type":"tag",
"tagName":"td",
"attrs":{
"rowSpan":"1",
"colSpan":"1"
},
"children":[
" ",
{
"type":"p",
"hlId":"c4c43b",
"class":"cell txt l",
"children":[
"Insomnia, weight loss, nausea, vomiting, and diarrhea"
]
},
" "
]
},
{
"type":"tag",
"tagName":"td",
"attrs":{
"rowSpan":"1",
"colSpan":"1"
},
"children":[
" ",
{
"type":"p",
"hlId":"1df10b",
"class":"cell txt l",
"children":[
"Aplastic anemia and hepatotoxicity",
{
"type":"tag",
"tagName":"sup",
"attrs":{
},
"children":[
"a"
]
}
]
},
" "
]
},
{
"type":"tag",
"tagName":"td",
"attrs":{
"rowSpan":"1",
"colSpan":"1"
},
"children":[
" ",
{
"type":"p",
"hlId":"68d312",
"class":"cell txt l",
"children":[
"CBC, liver chemistry studies"
]
},
" "
]
}
]
},
{
"type":"tag",
"tagName":"tr",
"attrs":{
"className":"group_1-3 row-odd"
},
"children":[
{
"type":"tag",
"tagName":"td",
"attrs":{
"rowSpan":"1",
"colSpan":"1"
},
"children":[
" ",
{
"type":"p",
"hlId":"364a98",
"class":"cell txt l",
"children":[
"Gabapentin and pregabalin"
]
},
" "
]
},
{
"type":"tag",
"tagName":"td",
"attrs":{
"rowSpan":"1",
"colSpan":"1"
},
"children":[
" ",
{
"type":"p",
"hlId":"0b30e6",
"class":"cell txt l",
"children":[
"Sedation, weight gain, edema, and dose-dependent dizziness"
]
},
" "
]
},
{
"type":"tag",
"tagName":"td",
"attrs":{
"rowSpan":"1",
"colSpan":"1"
},
"children":[
" ",
{
"type":"p",
"hlId":"26aeab",
"class":"cell txt l",
"children":[
"—"
]
},
" "
]
},
{
"type":"tag",
"tagName":"td",
"attrs":{
"rowSpan":"1",
"colSpan":"1"
},
"children":[
" ",
{
"type":"p",
"hlId":"26aeab",
"class":"cell txt l",
"children":[
"—"
]
},
" "
]
}
]
},
{
"type":"tag",
"tagName":"tr",
"attrs":{
"className":"group_1-4 row-even"
},
"children":[
{
"type":"tag",
"tagName":"td",
"attrs":{
"rowSpan":"1",
"colSpan":"1"
},
"children":[
" ",
{
"type":"p",
"hlId":"7fdc88",
"class":"cell txt l",
"children":[
"Lacosamide"
]
},
" "
]
},
{
"type":"tag",
"tagName":"td",
"attrs":{
"rowSpan":"1",
"colSpan":"1"
},
"children":[
" ",
{
"type":"p",
"hlId":"3e823c",
"class":"cell txt l",
"children":[
"Sedation, nausea, ataxia, tremor, diplopia, imbalance, headache, dose-dependent dizziness, and PR-interval prolongation"
]
},
" "
]
},
{
"type":"tag",
"tagName":"td",
"attrs":{
"rowSpan":"1",
"colSpan":"1"
},
"children":[
" ",
{
"type":"p",
"hlId":"af6165",
"class":"cell txt l",
"children":[
"Atrioventricular block, atrial fibrillation"
]
},
" "
]
},
{
"type":"tag",
"tagName":"td",
"attrs":{
"rowSpan":"1",
"colSpan":"1"
},
"children":[
" ",
{
"type":"p",
"hlId":"0cb215",
"class":"cell txt l",
"children":[
"ECG"
]
},
" "
]
}
]
},
{
"type":"tag",
"tagName":"tr",
"attrs":{
"className":"group_1-5 row-odd"
},
"children":[
{
"type":"tag",
"tagName":"td",
"attrs":{
"rowSpan":"1",
"colSpan":"1"
},
"children":[
" ",
{
"type":"p",
"hlId":"aeb6f9",
"class":"cell txt l",
"children":[
"Lamotrigine"
]
},
" "
]
},
{
"type":"tag",
"tagName":"td",
"attrs":{
"rowSpan":"1",
"colSpan":"1"
},
"children":[
" ",
{
"type":"p",
"hlId":"0f183a",
"class":"cell txt l",
"children":[
"Sedation, nausea, ataxia, tremor, diplopia, imbalance, headache, insomnia, and dose-dependent dizziness"
]
},
" "
]
},
{
"type":"tag",
"tagName":"td",
"attrs":{
"rowSpan":"1",
"colSpan":"1"
},
"children":[
" ",
{
"type":"p",
"hlId":"e6ce50",
"class":"cell txt l",
"children":[
"Rash"
]
},
" "
]
},
{
"type":"tag",
"tagName":"td",
"attrs":{
"rowSpan":"1",
"colSpan":"1"
},
"children":[
" ",
{
"type":"p",
"hlId":"b655db",
"class":"cell txt l",
"children":[
"Serum drug level"
]
},
" "
]
}
]
},
{
"type":"tag",
"tagName":"tr",
"attrs":{
"className":"group_1-6 row-even"
},
"children":[
{
"type":"tag",
"tagName":"td",
"attrs":{
"rowSpan":"1",
"colSpan":"1"
},
"children":[
" ",
{
"type":"p",
"hlId":"b17d3d",
"class":"cell txt l",
"children":[
"Levetiracetam and brivaracetam"
]
},
" "
]
},
{
"type":"tag",
"tagName":"td",
"attrs":{
"rowSpan":"1",
"colSpan":"1"
},
"children":[
" ",
{
"type":"p",
"hlId":"d8c5d2",
"class":"cell txt l",
"children":[
"Sedation, irritability, psychosis, and depression"
]
},
" "
]
},
{
"type":"tag",
"tagName":"td",
"attrs":{
"rowSpan":"1",
"colSpan":"1"
},
"children":[
" ",
{
"type":"p",
"hlId":"f5b204",
"class":"cell txt l",
"children":[
"Suicidal ideation",
{
"type":"tag",
"tagName":"sup",
"attrs":{
},
"children":[
"b"
]
},
" and thrombocytopenia (rare)"
]
},
" "
]
},
{
"type":"tag",
"tagName":"td",
"attrs":{
"rowSpan":"1",
"colSpan":"1"
},
"children":[
" ",
{
"type":"p",
"hlId":"26aeab",
"class":"cell txt l",
"children":[
"—"
]
},
" "
]
}
]
},
{
"type":"tag",
"tagName":"tr",
"attrs":{
"className":"group_1-7 row-odd"
},
"children":[
{
"type":"tag",
"tagName":"td",
"attrs":{
"rowSpan":"1",
"colSpan":"1"
},
"children":[
" ",
{
"type":"p",
"hlId":"9a835f",
"class":"cell txt l",
"children":[
"Perampanel"
]
},
" "
]
},
{
"type":"tag",
"tagName":"td",
"attrs":{
"rowSpan":"1",
"colSpan":"1"
},
"children":[
" ",
{
"type":"p",
"hlId":"69b5b1",
"class":"cell txt l",
"children":[
"Dizziness, headache, and sedation"
]
},
" "
]
},
{
"type":"tag",
"tagName":"td",
"attrs":{
"rowSpan":"1",
"colSpan":"1"
},
"children":[
" ",
{
"type":"p",
"hlId":"7ebf36",
"class":"cell txt l",
"children":[
"Homicidal ideation"
]
},
" "
]
},
{
"type":"tag",
"tagName":"td",
"attrs":{
"rowSpan":"1",
"colSpan":"1"
},
"children":[
" ",
{
"type":"p",
"hlId":"26aeab",
"class":"cell txt l",
"children":[
"—"
]
},
" "
]
}
]
},
{
"type":"tag",
"tagName":"tr",
"attrs":{
"className":"group_1-8 row-even"
},
"children":[
{
"type":"tag",
"tagName":"td",
"attrs":{
"rowSpan":"1",
"colSpan":"1"
},
"children":[
" ",
{
"type":"p",
"hlId":"4f0812",
"class":"cell txt l",
"children":[
"Phenobarbital"
]
},
" "
]
},
{
"type":"tag",
"tagName":"td",
"attrs":{
"rowSpan":"1",
"colSpan":"1"
},
"children":[
" ",
{
"type":"p",
"hlId":"b0f1a1",
"class":"cell txt l",
"children":[
"Sedation (but paradoxical hyperactivity in children)"
]
},
" "
]
},
{
"type":"tag",
"tagName":"td",
"attrs":{
"rowSpan":"1",
"colSpan":"1"
},
"children":[
" ",
{
"type":"p",
"hlId":"6c7bc8",
"class":"cell txt l",
"children":[
"Rash, pancytopenia, osteoporosis, hepatotoxicity"
]
},
" "
]
},
{
"type":"tag",
"tagName":"td",
"attrs":{
"rowSpan":"1",
"colSpan":"1"
},
"children":[
" ",
{
"type":"p",
"hlId":"535d9f",
"class":"cell txt l",
"children":[
"CBC, liver chemistry studies, bone density, serum drug level"
]
},
" "
]
}
]
},
{
"type":"tag",
"tagName":"tr",
"attrs":{
"className":"group_1-9 row-odd"
},
"children":[
{
"type":"tag",
"tagName":"td",
"attrs":{
"rowSpan":"1",
"colSpan":"1"
},
"children":[
" ",
{
"type":"p",
"hlId":"221fb3",
"class":"cell txt l",
"children":[
"Phenytoin"
]
},
" "
]
},
{
"type":"tag",
"tagName":"td",
"attrs":{
"rowSpan":"1",
"colSpan":"1"
},
"children":[
" ",
{
"type":"p",
"hlId":"290a2a",
"class":"cell txt l",
"children":[
"Sedation, nausea, ataxia, tremor, diplopia, imbalance, headache, and dose-dependent dizziness; if given IV, tissue necrosis (with extravasation), bradycardia, hypotension, and asystole"
]
},
" "
]
},
{
"type":"tag",
"tagName":"td",
"attrs":{
"rowSpan":"1",
"colSpan":"1"
},
"children":[
" ",
{
"type":"p",
"hlId":"60e0ac",
"class":"cell txt l",
"children":[
"Rash, gingival hyperplasia, cerebellar atrophy, peripheral neuropathy, pancytopenia, osteoporosis, hepatotoxicity"
]
},
" "
]
},
{
"type":"tag",
"tagName":"td",
"attrs":{
"rowSpan":"1",
"colSpan":"1"
},
"children":[
" ",
{
"type":"p",
"hlId":"535d9f",
"class":"cell txt l",
"children":[
"CBC, liver chemistry studies, bone density, serum drug level"
]
},
" "
]
}
]
},
{
"type":"tag",
"tagName":"tr",
"attrs":{
"className":"group_1-10 row-even"
},
"children":[
{
"type":"tag",
"tagName":"td",
"attrs":{
"rowSpan":"1",
"colSpan":"1"
},
"children":[
" ",
{
"type":"p",
"hlId":"8a0fba",
"class":"cell txt l",
"children":[
"Tiagabine"
]
},
" "
]
},
{
"type":"tag",
"tagName":"td",
"attrs":{
"rowSpan":"1",
"colSpan":"1"
},
"children":[
" ",
{
"type":"p",
"hlId":"a97305",
"class":"cell txt l",
"children":[
"Sedation, nausea, ataxia, tremor, diplopia, imbalance, headache, and dose-dependent dizziness"
]
},
" "
]
},
{
"type":"tag",
"tagName":"td",
"attrs":{
"rowSpan":"1",
"colSpan":"1"
},
"children":[
" ",
{
"type":"p",
"hlId":"1b1008",
"class":"cell txt l",
"children":[
"Acute confusion and encephalopathy"
]
},
" "
]
},
{
"type":"tag",
"tagName":"td",
"attrs":{
"rowSpan":"1",
"colSpan":"1"
},
"children":[
" ",
{
"type":"p",
"hlId":"8a0fba",
"class":"cell txt l",
"children":[
"Tiagabine"
]
},
" "
]
}
]
},
{
"type":"tag",
"tagName":"tr",
"attrs":{
"className":"group_1-11 row-odd"
},
"children":[
{
"type":"tag",
"tagName":"td",
"attrs":{
"rowSpan":"1",
"colSpan":"1"
},
"children":[
" ",
{
"type":"p",
"hlId":"fb51a7",
"class":"cell txt l",
"children":[
"Topiramate and zonisamide"
]
},
" "
]
},
{
"type":"tag",
"tagName":"td",
"attrs":{
"rowSpan":"1",
"colSpan":"1"
},
"children":[
" ",
{
"type":"p",
"hlId":"193233",
"class":"cell txt l",
"children":[
"Sedation, nausea, ataxia, tremor, diplopia, imbalance, headache, word finding difficulty, poor concentration, paresthesias, weight loss, anhidrosis, and dose-dependent dizziness"
]
},
" "
]
},
{
"type":"tag",
"tagName":"td",
"attrs":{
"rowSpan":"1",
"colSpan":"1"
},
"children":[
" ",
{
"type":"p",
"hlId":"dfb996",
"class":"cell txt l",
"children":[
"Nephrolithiasis, acute angle glaucoma, psychosis"
]
},
" "
]
},
{
"type":"tag",
"tagName":"td",
"attrs":{
"rowSpan":"1",
"colSpan":"1"
},
"children":[
" ",
{
"type":"p",
"hlId":"d53ff4",
"class":"cell txt l",
"children":[
"BMP in select cases"
]
},
" "
]
}
]
},
{
"type":"tag",
"tagName":"tr",
"attrs":{
"className":"group_1-12 row-even"
},
"children":[
{
"type":"tag",
"tagName":"td",
"attrs":{
"rowSpan":"1",
"colSpan":"1"
},
"children":[
" ",
{
"type":"p",
"hlId":"83bef1",
"class":"cell txt l",
"children":[
"Valproic acid"
]
},
" "
]
},
{
"type":"tag",
"tagName":"td",
"attrs":{
"rowSpan":"1",
"colSpan":"1"
},
"children":[
" ",
{
"type":"p",
"hlId":"4deba7",
"class":"cell txt l",
"children":[
"Sedation, nausea, ataxia, tremor, diplopia, imbalance, headache, and dose-dependent dizziness; weight gain, hair loss, PCOS, and reversible parkinsonism with dementia"
]
},
" "
]
},
{
"type":"tag",
"tagName":"td",
"attrs":{
"rowSpan":"1",
"colSpan":"1"
},
"children":[
" ",
{
"type":"p",
"hlId":"640cac",
"class":"cell txt l",
"children":[
"Pancytopenia, osteoporosis, hepatotoxicity, pancreatitis, hyperammonemia"
]
},
" "
]
},
{
"type":"tag",
"tagName":"td",
"attrs":{
"rowSpan":"1",
"colSpan":"1"
},
"children":[
" ",
{
"type":"p",
"hlId":"564c23",
"class":"cell txt l",
"children":[
"CBC, liver chemistry studies, bone density, serum drug level, serum ammonia level in select cases"
]
},
" "
]
}
]
}
]
}
]
},
"footnotes":[
[
"BMP = basic metabolic profile; CBC = complete blood count; IV, intravenously; PCOS = polycystic ovary syndrome."
],
[
{
"type":"tag",
"tagName":"sup",
"attrs":{
},
"children":[
"a"
]
},
"A serious and potentially fatal adverse effect that limits this drug's use (and requires close monitoring)."
],
[
{
"type":"tag",
"tagName":"sup",
"attrs":{
},
"children":[
"b"
]
},
"A concern with all antiepileptic drugs, but especially levetiracetam."
]
]
}