{
"id":"mk19_b_gm_t53",
"number":53,
"bookId":"gm2",
"title":{
"__html":"Common Causes of Chronic Pelvic Pain"
},
"jsonContent":{
"type":"tag",
"tagName":"table",
"attrs":{
"className":"table"
},
"children":[
{
"type":"tag",
"tagName":"caption",
"attrs":{
},
"children":[
{
"type":"p",
"hlId":"b728fb",
"children":[
{
"type":"tag",
"tagName":"b",
"attrs":{
"className":"table-number"
},
"children":[
{
"type":"tag",
"tagName":"span",
"attrs":{
},
"children":[
"Table 53. "
]
},
{
"type":"new-window-link",
"targetType":"table",
"targetId":"mk19_b_gm_t53"
}
]
},
"Common Causes of Chronic Pelvic Pain"
]
}
]
},
{
"type":"tag",
"tagName":"thead",
"attrs":{
},
"children":[
{
"type":"tag",
"tagName":"tr",
"attrs":{
},
"children":[
{
"type":"tag",
"tagName":"th",
"attrs":{
"rowSpan":"1",
"colSpan":"1"
},
"children":[
" ",
{
"type":"p",
"hlId":"e30934",
"class":"col hd l",
"children":[
"Gynecologic Causes"
]
},
" "
]
}
]
}
]
},
{
"type":"tag",
"tagName":"tbody",
"attrs":{
},
"children":[
{
"type":"tag",
"tagName":"tr",
"attrs":{
},
"children":[
{
"type":"tag",
"tagName":"td",
"attrs":{
"rowSpan":"1",
"colSpan":"1"
},
"children":[
" ",
{
"type":"p",
"hlId":"41b2cc",
"class":"cell txt l",
"children":[
"Endometriosis"
]
},
" ",
{
"type":"p",
"hlId":"63e3e9",
"class":"cell txt l",
"children":[
"Pelvic adhesions"
]
},
" ",
{
"type":"p",
"hlId":"530f7e",
"class":"cell txt l",
"children":[
"Chronic pelvic inflammatory disease"
]
},
" ",
{
"type":"p",
"hlId":"9711f8",
"class":"cell txt l",
"children":[
"Adenomyosis"
]
},
" ",
{
"type":"p",
"hlId":"7d9488",
"class":"cell txt l",
"children":[
"Vulvodynia"
]
},
" ",
{
"type":"p",
"hlId":"6e3ba5",
"class":"cell txt l",
"children":[
"Ovarian cysts"
]
},
" ",
{
"type":"p",
"hlId":"33c742",
"class":"cell txt l",
"children":[
"Uterine myoma (fibroid)"
]
},
" "
]
}
]
},
{
"type":"tag",
"tagName":"tr",
"attrs":{
},
"children":[
{
"type":"tag",
"tagName":"th",
"attrs":{
"rowSpan":"1",
"colSpan":"1"
},
"children":[
" ",
{
"type":"p",
"hlId":"dd7d42",
"class":"col hd l",
"children":[
"Urologic Causes"
]
},
" "
]
}
]
},
{
"type":"tag",
"tagName":"tr",
"attrs":{
},
"children":[
{
"type":"tag",
"tagName":"td",
"attrs":{
"rowSpan":"1",
"colSpan":"1"
},
"children":[
" ",
{
"type":"p",
"hlId":"a1e05f",
"class":"cell txt l",
"children":[
"Interstitial cystitis/painful bladder syndrome"
]
},
" ",
{
"type":"p",
"hlId":"1bafbd",
"class":"cell txt l",
"children":[
"Radiation cystitis"
]
},
" ",
{
"type":"p",
"hlId":"89ca71",
"class":"cell txt l",
"children":[
"Urethral syndrome"
]
},
" ",
{
"type":"p",
"hlId":"748bee",
"class":"cell txt l",
"children":[
"Urinary calculi"
]
},
" "
]
}
]
},
{
"type":"tag",
"tagName":"tr",
"attrs":{
},
"children":[
{
"type":"tag",
"tagName":"th",
"attrs":{
"rowSpan":"1",
"colSpan":"1"
},
"children":[
" ",
{
"type":"p",
"hlId":"fb60b9",
"class":"col hd l",
"children":[
"Gastrointestinal Causes"
]
},
" "
]
}
]
},
{
"type":"tag",
"tagName":"tr",
"attrs":{
},
"children":[
{
"type":"tag",
"tagName":"td",
"attrs":{
"rowSpan":"1",
"colSpan":"1"
},
"children":[
" ",
{
"type":"p",
"hlId":"521d73",
"class":"cell txt l",
"children":[
"Irritable bowel syndrome"
]
},
" ",
{
"type":"p",
"hlId":"271f14",
"class":"cell txt l",
"children":[
"Inflammatory bowel disease"
]
},
" ",
{
"type":"p",
"hlId":"a5cb00",
"class":"cell txt l",
"children":[
"Chronic constipation"
]
},
" ",
{
"type":"p",
"hlId":"41ee8c",
"class":"cell txt l",
"children":[
"Diverticulitis"
]
},
" ",
{
"type":"p",
"hlId":"6b2970",
"class":"cell txt l",
"children":[
"Celiac disease"
]
},
" "
]
}
]
},
{
"type":"tag",
"tagName":"tr",
"attrs":{
},
"children":[
{
"type":"tag",
"tagName":"th",
"attrs":{
"rowSpan":"1",
"colSpan":"1"
},
"children":[
" ",
{
"type":"p",
"hlId":"d66bd4",
"class":"col hd l",
"children":[
"Musculoskeletal/Neurologic Causes"
]
},
" "
]
}
]
},
{
"type":"tag",
"tagName":"tr",
"attrs":{
},
"children":[
{
"type":"tag",
"tagName":"td",
"attrs":{
"rowSpan":"1",
"colSpan":"1"
},
"children":[
" ",
{
"type":"p",
"hlId":"eeede8",
"class":"cell txt l",
"children":[
"Myofascial pain syndromes"
]
},
" ",
{
"type":"p",
"hlId":"a24e07",
"class":"cell txt l",
"children":[
"Fibromyalgia"
]
},
" ",
{
"type":"p",
"hlId":"b48f10",
"class":"cell txt l",
"children":[
"Chronic coccygeal pain"
]
},
" ",
{
"type":"p",
"hlId":"a542dc",
"class":"cell txt l",
"children":[
"Chronic low back pain"
]
},
" ",
{
"type":"p",
"hlId":"ff404b",
"class":"cell txt l",
"children":[
"Piriformis syndrome"
]
},
" ",
{
"type":"p",
"hlId":"449e6f",
"class":"cell txt l",
"children":[
"Neuralgia"
]
},
" "
]
}
]
}
]
}
]
},
"footnotes":[

]
}