{
"id":"mk19_a_id_t31",
"number":31,
"bookId":"id",
"title":{
"__html":"Treatment of Herpes Simplex Virus Genital Infections"
},
"jsonContent":{
"type":"tag",
"tagName":"table",
"attrs":{
"className":"table"
},
"children":[
{
"type":"tag",
"tagName":"caption",
"attrs":{
},
"children":[
{
"type":"p",
"hlId":"08dcd7",
"children":[
{
"type":"tag",
"tagName":"b",
"attrs":{
"className":"table-number"
},
"children":[
{
"type":"tag",
"tagName":"span",
"attrs":{
},
"children":[
"Table 31. "
]
},
{
"type":"new-window-link",
"targetType":"table",
"targetId":"mk19_a_id_t31"
}
]
},
"Treatment of Herpes Simplex Virus Genital Infections"
]
}
]
},
{
"type":"tag",
"tagName":"thead",
"attrs":{
},
"children":[
{
"type":"tag",
"tagName":"tr",
"attrs":{
},
"children":[
{
"type":"tag",
"tagName":"th",
"attrs":{
"rowSpan":"1",
"colSpan":"1"
},
"children":[
" ",
{
"type":"p",
"hlId":"c4099c",
"class":"col hd l",
"children":[
"Clinical Syndrome"
]
},
" "
]
},
{
"type":"tag",
"tagName":"th",
"attrs":{
"rowSpan":"1",
"colSpan":"1"
},
"children":[
" ",
{
"type":"p",
"hlId":"2594be",
"class":"col hd l",
"children":[
"Recommended Regimen",
{
"type":"tag",
"tagName":"sup",
"attrs":{
},
"children":[
"a"
]
}
]
},
" "
]
}
]
}
]
},
{
"type":"tag",
"tagName":"tbody",
"attrs":{
},
"children":[
{
"type":"tag",
"tagName":"tr",
"attrs":{
"className":"group_1-1 row-odd"
},
"children":[
{
"type":"tag",
"tagName":"td",
"attrs":{
"rowSpan":"1",
"colSpan":"1"
},
"children":[
" ",
{
"type":"p",
"hlId":"ab3a04",
"class":"cell txt l",
"children":[
"Primary infection",
{
"type":"tag",
"tagName":"sup",
"attrs":{
},
"children":[
"b"
]
}
]
},
" "
]
},
{
"type":"tag",
"tagName":"td",
"attrs":{
"rowSpan":"1",
"colSpan":"1"
},
"children":[
" ",
{
"type":"p",
"hlId":"70155a",
"class":"cell txt l",
"children":[
"Acyclovir, 400 mg three times daily, ",
{
"type":"tag",
"tagName":"i",
"attrs":{
},
"children":[
"or"
]
},
" acyclovir, 200 mg five times daily",
{
"type":"tag",
"tagName":"sup",
"attrs":{
},
"children":[
"c"
]
},
", ",
{
"type":"tag",
"tagName":"i",
"attrs":{
},
"children":[
"or"
]
},
" famciclovir, 250 mg three times daily, ",
{
"type":"tag",
"tagName":"i",
"attrs":{
},
"children":[
"or"
]
},
" valacyclovir, 1 g twice daily; all regimens for 7-10 days"
]
},
" "
]
}
]
},
{
"type":"tag",
"tagName":"tr",
"attrs":{
"className":"group_1-2 row-even"
},
"children":[
{
"type":"tag",
"tagName":"td",
"attrs":{
"rowSpan":"1",
"colSpan":"1"
},
"children":[
" ",
{
"type":"p",
"hlId":"76a512",
"class":"cell txt l",
"children":[
"Episodic treatment for recurrent infection"
]
},
" "
]
},
{
"type":"tag",
"tagName":"td",
"attrs":{
"rowSpan":"1",
"colSpan":"1"
},
"children":[
" ",
{
"type":"p",
"hlId":"191076",
"class":"cell txt l",
"children":[
"Acyclovir, 400 mg three times daily for 5 days",
{
"type":"tag",
"tagName":"sup",
"attrs":{
},
"children":[
"c"
]
},
", ",
{
"type":"tag",
"tagName":"i",
"attrs":{
},
"children":[
"or"
]
},
" acyclovir, 800 mg twice daily for 5 days, ",
{
"type":"tag",
"tagName":"i",
"attrs":{
},
"children":[
"or"
]
},
" acyclovir, 800 mg three times daily for 2 days, ",
{
"type":"tag",
"tagName":"i",
"attrs":{
},
"children":[
"or"
]
},
" famciclovir, 125 mg twice daily for 5 days, ",
{
"type":"tag",
"tagName":"i",
"attrs":{
},
"children":[
"or"
]
},
" famciclovir, 1 g twice daily for 1 day, ",
{
"type":"tag",
"tagName":"i",
"attrs":{
},
"children":[
"or"
]
},
" famciclovir, 500 mg once followed by 250 mg twice daily for 2 days, ",
{
"type":"tag",
"tagName":"i",
"attrs":{
},
"children":[
"or"
]
},
" valacyclovir, 500 mg twice daily for 3 days, ",
{
"type":"tag",
"tagName":"i",
"attrs":{
},
"children":[
"or"
]
},
" valacyclovir, 1 g once daily for 5 days"
]
},
" "
]
}
]
},
{
"type":"tag",
"tagName":"tr",
"attrs":{
"className":"group_1-3 row-odd"
},
"children":[
{
"type":"tag",
"tagName":"td",
"attrs":{
"rowSpan":"1",
"colSpan":"1"
},
"children":[
" ",
{
"type":"p",
"hlId":"807c96",
"class":"cell txt l",
"children":[
"Suppressive therapy for recurrent infection"
]
},
" "
]
},
{
"type":"tag",
"tagName":"td",
"attrs":{
"rowSpan":"1",
"colSpan":"1"
},
"children":[
" ",
{
"type":"p",
"hlId":"e93704",
"class":"cell txt l",
"children":[
"Acyclovir, 400 mg twice daily, ",
{
"type":"tag",
"tagName":"i",
"attrs":{
},
"children":[
"or"
]
},
" famciclovir, 250 mg twice daily, ",
{
"type":"tag",
"tagName":"i",
"attrs":{
},
"children":[
"or"
]
},
" valacyclovir, 500 mg daily",
{
"type":"tag",
"tagName":"sup",
"attrs":{
},
"children":[
"d"
]
},
", ",
{
"type":"tag",
"tagName":"i",
"attrs":{
},
"children":[
"or"
]
},
" valacyclovir, 1 g daily"
]
},
" "
]
}
]
}
]
}
]
},
"footnotes":[
[
{
"type":"tag",
"tagName":"sup",
"attrs":{
},
"children":[
"a"
]
},
"All regimens are given orally; topical preparations are not recommended for treatment of genital herpes simplex virus."
],
[
{
"type":"tag",
"tagName":"sup",
"attrs":{
},
"children":[
"b"
]
},
"Therapy can be extended if healing is incomplete after 10 days of treatment."
],
[
{
"type":"tag",
"tagName":"sup",
"attrs":{
},
"children":[
"c"
]
},
"According to 2021 CDC guidelines, these acyclovir dosages are effective but are not recommended because of dosing frequency."
],
[
{
"type":"tag",
"tagName":"sup",
"attrs":{
},
"children":[
"d"
]
},
"The 500-mg dose of valacyclovir may be less effective than the 1-g dose in patients who have very frequent recurrences (≥10 episodes per year)."
]
]
}